<?xml version="1.0" encoding="UTF-8"?>

<CHAT xmlns:xsi="http://www.w3.org/2001/XMLSchema-instance"
      xmlns="http://www.talkbank.org/ns/talkbank"
      xsi:schemaLocation="http://www.talkbank.org/ns/talkbank https://talkbank.org/software/talkbank.xsd"
            DesignType="long"
            ActivityType="toyplay"
            GroupType="TD"
      PID="11312/c-00020360-1"
      Version="2.16.0"
      Lang="eng"
      Corpus="Wells"
      >
  <Participants>
    <participant
      id="CHI"
    name="Tony"
      role="Target_Child"
      language="eng"
      age="P1Y08M26D"
      sex="male"

    />
    <participant
      id="MOT"
      role="Mother"
      language="eng"
      sex="female"

    />
    <participant
      id="FAT"
      role="Father"
      language="eng"
      sex="male"

    />
    <participant
      id="GRA"
      role="Grandfather"
      language="eng"

    />
  </Participants>
  <comment type="Activities">Free play</comment>
  <comment type="Situation">T and Gf are in the garden. T has a toy sweeping brush and is rushing up and down with it , making excited noises</comment>
  <comment type="Types">long, toyplay, TD</comment>
  <u who="GRA" uID="u0">
    <w>you<mor type="mor"><mw><pos><c>pro</c><s>per</s></pos><stem>you</stem></mw><gra type="gra" index="1" head="2" relation="SUBJ"/></mor></w>
    <w>are<mor type="mor"><mw><pos><c>cop</c></pos><stem>be</stem><mk type="sfxf">PRES</mk></mw><gra type="gra" index="2" head="0" relation="ROOT"/></mor></w>
    <w>a<mor type="mor"><mw><pos><c>det</c><s>art</s></pos><stem>a</stem></mw><gra type="gra" index="3" head="6" relation="DET"/></mor></w>
    <w>busy<mor type="mor"><mw><pos><c>adj</c></pos><stem>busy</stem></mw><gra type="gra" index="4" head="6" relation="MOD"/></mor></w>
    <w>little<mor type="mor"><mw><pos><c>adj</c></pos><stem>little</stem></mw><gra type="gra" index="5" head="6" relation="MOD"/></mor></w>
    <w>man<mor type="mor"><mw><pos><c>n</c></pos><stem>man</stem></mw><gra type="gra" index="6" head="2" relation="PRED"/></mor></w>
    <t type="p"><mor type="mor"><mt type="p"/><gra type="gra" index="7" head="2" relation="PUNCT"/></mor></t>

  </u>
  <u who="GRA" uID="u1">
    <w>busy<mor type="mor"><mw><pos><c>adj</c></pos><stem>busy</stem></mw><gra type="gra" index="1" head="3" relation="MOD"/></mor></w>
    <w>little<mor type="mor"><mw><pos><c>adj</c></pos><stem>little</stem></mw><gra type="gra" index="2" head="3" relation="MOD"/></mor></w>
    <w>man<mor type="mor"><mw><pos><c>n</c></pos><stem>man</stem></mw><gra type="gra" index="3" head="0" relation="INCROOT"/></mor></w>
    <pause symbolic-length="simple" length="4"/>
    <t type="p"><mor type="mor"><mt type="p"/><gra type="gra" index="4" head="3" relation="PUNCT"/></mor></t>

    <a type="paralinguistics">&lt;aft&gt; breathless noises</a>
    <a type="comments">bell rings maybe like a toy telephone</a>
  </u>
  <u who="MOT" uID="u2">
    <w>going<mor type="mor"><mw><pos><c>part</c></pos><stem>go</stem><mk type="sfx">PRESP</mk></mw><gra type="gra" index="1" head="0" relation="INCROOT"/></mor></w>
    <w>to<mor type="mor"><mw><pos><c>inf</c></pos><stem>to</stem></mw><gra type="gra" index="2" head="3" relation="INF"/></mor></w>
    <w>put<mor type="mor"><mw><pos><c>v</c></pos><stem>put</stem><mk type="sfxf">ZERO</mk></mw><gra type="gra" index="3" head="1" relation="COMP"/></mor></w>
    <w>the<mor type="mor"><mw><pos><c>det</c><s>art</s></pos><stem>the</stem></mw><gra type="gra" index="4" head="5" relation="DET"/></mor></w>
    <w>washing<mor type="mor"><mw><pos><c>n</c><s>gerund</s></pos><stem>wash</stem><mk type="sfx">PRESP</mk></mw><gra type="gra" index="5" head="3" relation="OBJ"/></mor></w>
    <w>out<mor type="mor"><mw><pos><c>adv</c></pos><stem>out</stem></mw><gra type="gra" index="6" head="3" relation="JCT"/></mor></w>
    <w>for<mor type="mor"><mw><pos><c>prep</c></pos><stem>for</stem></mw><gra type="gra" index="7" head="3" relation="JCT"/></mor></w>
    <w>me<mor type="mor"><mw><pos><c>pro</c><s>obj</s></pos><stem>me</stem></mw><gra type="gra" index="8" head="7" relation="POBJ"/></mor></w>
    <t type="q"><mor type="mor"><mt type="q"/><gra type="gra" index="9" head="1" relation="PUNCT"/></mor></t>

  </u>
  <u who="MOT" uID="u3">
    <w>oh<mor type="mor"><mw><pos><c>co</c></pos><stem>oh</stem></mw><gra type="gra" index="1" head="2" relation="COM"/></mor></w>
    <w>yes<mor type="mor"><mw><pos><c>co</c></pos><stem>yes</stem></mw><gra type="gra" index="2" head="0" relation="INCROOT"/></mor></w>
    <pause symbolic-length="simple" length="4"/>
    <t type="p"><mor type="mor"><mt type="p"/><gra type="gra" index="3" head="2" relation="PUNCT"/></mor></t>

    <a type="addressee">to T</a>
  </u>
  <u who="GRA" uID="u4">
    <w>what's<mor type="mor"><mw><pos><c>pro</c><s>int</s></pos><stem>what</stem></mw><gra type="gra" index="1" head="2" relation="SUBJ"/><mor-post><mw><pos><c>cop</c></pos><stem>be</stem><mk type="sfxf">3S</mk></mw><gra type="gra" index="2" head="0" relation="ROOT"/></mor-post></mor></w>
    <w>in<mor type="mor"><mw><pos><c>prep</c></pos><stem>in</stem></mw><gra type="gra" index="3" head="2" relation="JCT"/></mor></w>
    <w>your<mor type="mor"><mw><pos><c>det</c><s>poss</s></pos><stem>your</stem></mw><gra type="gra" index="4" head="6" relation="DET"/></mor></w>
    <w>long<mor type="mor"><mw><pos><c>adj</c></pos><stem>long</stem></mw><gra type="gra" index="5" head="6" relation="MOD"/></mor></w>
    <w>cloche<mor type="mor"><mw><pos><c>n</c></pos><stem>cloche</stem></mw><gra type="gra" index="6" head="3" relation="POBJ"/></mor></w>
    <t type="q"><mor type="mor"><mt type="q"/><gra type="gra" index="7" head="2" relation="PUNCT"/></mor></t>

    <a type="paralinguistics">&lt;1.&gt; shrieks &lt;1.&gt; cries</a>
    <a type="comments">t can be heard rushing about Pretends he can't come down a ramp into the garden</a>
  </u>
  <u who="MOT" uID="u5">
    <w>come<mor type="mor"><mw><pos><c>v</c></pos><stem>come</stem></mw><gra type="gra" index="1" head="0" relation="ROOT"/></mor></w>
    <w>on<mor type="mor"><mw><pos><c>adv</c></pos><stem>on</stem></mw><gra type="gra" index="2" head="1" relation="JCT"/></mor></w>
    <w>down<mor type="mor"><mw><pos><c>prep</c></pos><stem>down</stem></mw><gra type="gra" index="3" head="1" relation="JCT"/></mor></w>
    <w>here<mor type="mor"><mw><pos><c>adv</c></pos><stem>here</stem></mw><gra type="gra" index="4" head="3" relation="POBJ"/></mor></w>
    <pause symbolic-length="simple" length="12"/>
    <t type="p"><mor type="mor"><mt type="p"/><gra type="gra" index="5" head="1" relation="PUNCT"/></mor></t>

    <a type="paralinguistics">&lt;aft&gt; pretending &lt;aft&gt; cries</a>
  </u>
  <u who="MOT" uID="u6">
    <w>don't<mor type="mor"><mw><pos><c>mod</c></pos><stem>do</stem></mw><gra type="gra" index="1" head="3" relation="AUX"/><mor-post><mw><pos><c>neg</c></pos><stem>not</stem></mw><gra type="gra" index="2" head="1" relation="NEG"/></mor-post></mor></w>
    <w>be<mor type="mor"><mw><pos><c>cop</c></pos><stem>be</stem></mw><gra type="gra" index="3" head="0" relation="ROOT"/></mor></w>
    <w>so<mor type="mor"><mw><pos><c>adv</c></pos><stem>so</stem></mw><gra type="gra" index="4" head="5" relation="JCT"/></mor></w>
    <w>silly<mor type="mor"><mw><pos><c>adj</c></pos><stem>silly</stem></mw><gra type="gra" index="5" head="6" relation="MOD"/></mor></w>
    <w>Tony<mor type="mor"><mw><pos><c>n</c><s>prop</s></pos><stem>Tony</stem></mw><gra type="gra" index="6" head="3" relation="PRED"/></mor></w>
    <t type="p"><mor type="mor"><mt type="p"/><gra type="gra" index="7" head="3" relation="PUNCT"/></mor></t>

    <a type="comments">down the ramp</a>
  </u>
  <comment type="Activities">Free play</comment>
  <comment type="Situation">T is playing in the kitchen with a toy bus</comment>
  <u who="GRA" uID="u7">
    <w untranscribed="unintelligible">xxx</w>
    <t type="p"></t>

  </u>
  <u who="MOT" uID="u8">
    <w>I<mor type="mor"><mw><pos><c>pro</c><s>sub</s></pos><stem>I</stem></mw><gra type="gra" index="1" head="4" relation="SUBJ"/></mor></w>
    <w>shouldn't<mor type="mor"><mw><pos><c>mod</c></pos><stem>should</stem></mw><gra type="gra" index="2" head="4" relation="AUX"/><mor-post><mw><pos><c>neg</c></pos><stem>not</stem></mw><gra type="gra" index="3" head="2" relation="NEG"/></mor-post></mor></w>
    <w>do<mor type="mor"><mw><pos><c>v</c></pos><stem>do</stem></mw><gra type="gra" index="4" head="0" relation="ROOT"/></mor></w>
    <w>it<mor type="mor"><mw><pos><c>pro</c><s>per</s></pos><stem>it</stem></mw><gra type="gra" index="5" head="4" relation="OBJ"/></mor></w>
    <w>on<mor type="mor"><mw><pos><c>prep</c></pos><stem>on</stem></mw><gra type="gra" index="6" head="4" relation="JCT"/></mor></w>
    <w>the<mor type="mor"><mw><pos><c>det</c><s>art</s></pos><stem>the</stem></mw><gra type="gra" index="7" head="8" relation="DET"/></mor></w>
    <w>door<mor type="mor"><mw><pos><c>n</c></pos><stem>door</stem></mw><gra type="gra" index="8" head="6" relation="POBJ"/></mor></w>
    <t type="p"><mor type="mor"><mt type="p"/><gra type="gra" index="9" head="4" relation="PUNCT"/></mor></t>

  </u>
  <u who="MOT" uID="u9">
    <w>no<mor type="mor"><mw><pos><c>co</c></pos><stem>no</stem></mw><gra type="gra" index="1" head="0" relation="INCROOT"/></mor></w>
    <pause symbolic-length="simple" length="15"/>
    <t type="p"><mor type="mor"><mt type="p"/><gra type="gra" index="2" head="1" relation="PUNCT"/></mor></t>

  </u>
  <u who="MOT" uID="u10">
    <w>oh<mor type="mor"><mw><pos><c>co</c></pos><stem>oh</stem></mw><gra type="gra" index="1" head="0" relation="INCROOT"/></mor></w>
    <t type="p"><mor type="mor"><mt type="p"/><gra type="gra" index="2" head="1" relation="PUNCT"/></mor></t>

  </u>
  <u who="GRA" uID="u11">
    <w>zzz<mor type="mor"><mw><pos><c>co</c></pos><stem>zzz</stem></mw><gra type="gra" index="1" head="0" relation="INCROOT"/></mor></w>
    <t type="p"><mor type="mor"><mt type="p"/><gra type="gra" index="2" head="1" relation="PUNCT"/></mor></t>

  </u>
  <u who="GRA" uID="u12">
    <e><action/><ga type="paralinguistics">laughing</ga></e>
    <t type="p"></t>

  </u>
  <u who="GRA" uID="u13">
    <w type="filler">eh</w>
    <t type="q"></t>

  </u>
  <u who="GRA" uID="u14">
    <w>oh<mor type="mor"><mw><pos><c>co</c></pos><stem>oh</stem></mw><gra type="gra" index="1" head="0" relation="INCROOT"/></mor></w>
    <t type="p"><mor type="mor"><mt type="p"/><gra type="gra" index="2" head="1" relation="PUNCT"/></mor></t>

  </u>
  <u who="GRA" uID="u15">
    <w>you've<mor type="mor"><mw><pos><c>pro</c><s>per</s></pos><stem>you</stem></mw><gra type="gra" index="1" head="3" relation="SUBJ"/><mor-post><mw><pos><c>aux</c></pos><stem>have</stem></mw><gra type="gra" index="2" head="3" relation="AUX"/></mor-post></mor></w>
    <w>broken<mor type="mor"><mw><pos><c>part</c></pos><stem>break</stem><mk type="sfxf">PASTP</mk></mw><gra type="gra" index="3" head="0" relation="ROOT"/></mor></w>
    <w>it<mor type="mor"><mw><pos><c>pro</c><s>per</s></pos><stem>it</stem></mw><gra type="gra" index="4" head="7" relation="SUBJ"/></mor></w>
    <w>haven't<mor type="mor"><mw><pos><c>aux</c></pos><stem>have</stem></mw><gra type="gra" index="5" head="7" relation="AUX"/><mor-post><mw><pos><c>neg</c></pos><stem>not</stem></mw><gra type="gra" index="6" head="5" relation="NEG"/></mor-post></mor></w>
    <w>you<mor type="mor"><mw><pos><c>pro</c><s>per</s></pos><stem>you</stem></mw><gra type="gra" index="7" head="3" relation="OBJ"/></mor></w>
    <t type="q"><mor type="mor"><mt type="q"/><gra type="gra" index="8" head="3" relation="PUNCT"/></mor></t>

  </u>
  <u who="GRA" uID="u16">
    <w>yes<mor type="mor"><mw><pos><c>co</c></pos><stem>yes</stem></mw><gra type="gra" index="1" head="0" relation="INCROOT"/></mor></w>
    <t type="p"><mor type="mor"><mt type="p"/><gra type="gra" index="2" head="1" relation="PUNCT"/></mor></t>

  </u>
  <u who="MOT" uID="u17">
    <w>I<mor type="mor"><mw><pos><c>pro</c><s>sub</s></pos><stem>I</stem></mw><gra type="gra" index="1" head="4" relation="SUBJ"/></mor></w>
    <w>don't<mor type="mor"><mw><pos><c>mod</c></pos><stem>do</stem></mw><gra type="gra" index="2" head="4" relation="AUX"/><mor-post><mw><pos><c>neg</c></pos><stem>not</stem></mw><gra type="gra" index="3" head="2" relation="NEG"/></mor-post></mor></w>
    <w>think<mor type="mor"><mw><pos><c>v</c></pos><stem>think</stem></mw><gra type="gra" index="4" head="0" relation="ROOT"/></mor></w>
    <w>it<mor type="mor"><mw><pos><c>pro</c><s>per</s></pos><stem>it</stem></mw><gra type="gra" index="5" head="6" relation="SUBJ"/></mor></w>
    <w>was<mor type="mor"><mw><pos><c>cop</c></pos><stem>be</stem><mk type="sfxf">PAST</mk><mk type="sfxf">13S</mk></mw><gra type="gra" index="6" head="4" relation="COMP"/></mor></w>
    <w>Tony<mor type="mor"><mw><pos><c>n</c><s>prop</s></pos><stem>Tony</stem></mw><gra type="gra" index="7" head="6" relation="PRED"/></mor></w>
    <t type="p"><mor type="mor"><mt type="p"/><gra type="gra" index="8" head="4" relation="PUNCT"/></mor></t>

    <a type="paralinguistics">&lt;aft&gt; noises</a>
  </u>
  <u who="MOT" uID="u18">
    <g><w untranscribed="unintelligible">xxx</w><overlap type="overlap precedes"/></g>
    <w>one<mor type="mor"><mw><pos><c>det</c><s>num</s></pos><stem>one</stem></mw><gra type="gra" index="1" head="0" relation="INCROOT"/></mor></w>
    <w>of<mor type="mor"><mw><pos><c>prep</c></pos><stem>of</stem></mw><gra type="gra" index="2" head="1" relation="JCT"/></mor></w>
    <w>the<mor type="mor"><mw><pos><c>det</c><s>art</s></pos><stem>the</stem></mw><gra type="gra" index="3" head="5" relation="DET"/></mor></w>
    <w>other<mor type="mor"><mw><pos><c>qn</c></pos><stem>other</stem></mw><gra type="gra" index="4" head="5" relation="QUANT"/></mor></w>
    <w>kids<mor type="mor"><mw><pos><c>n</c></pos><stem>kid</stem><mk type="sfx">PL</mk></mw><gra type="gra" index="5" head="2" relation="POBJ"/></mor></w>
    <pause symbolic-length="simple" length="3"/>
    <t type="p"><mor type="mor"><mt type="p"/><gra type="gra" index="6" head="1" relation="PUNCT"/></mor></t>

  </u>
  <u who="GRA" uID="u19">
    <w>rather<mor type="mor"><mw><pos><c>adv</c></pos><stem>rather</stem></mw><gra type="gra" index="1" head="4" relation="JCT"/></mor></w>
    <w>a<mor type="mor"><mw><pos><c>det</c><s>art</s></pos><stem>a</stem></mw><gra type="gra" index="2" head="4" relation="DET"/></mor></w>
    <w>good<mor type="mor"><mw><pos><c>adj</c></pos><stem>good</stem></mw><gra type="gra" index="3" head="4" relation="MOD"/></mor></w>
    <w>bus<mor type="mor"><mw><pos><c>n</c></pos><stem>bus</stem></mw><gra type="gra" index="4" head="0" relation="INCROOT"/></mor></w>
    <w>though<mor type="mor"><mw><pos><c>conj</c></pos><stem>though</stem></mw><gra type="gra" index="5" head="7" relation="LINK"/></mor></w>
    <w>that<mor type="mor"><mw><pos><c>pro</c><s>dem</s></pos><stem>that</stem></mw><gra type="gra" index="6" head="7" relation="SUBJ"/></mor></w>
    <w>is<mor type="mor"><mw><pos><c>cop</c></pos><stem>be</stem><mk type="sfxf">3S</mk></mw><gra type="gra" index="7" head="4" relation="CMOD"/></mor></w>
    <w>isn't<mor type="mor"><mw><pos><c>cop</c></pos><stem>be</stem><mk type="sfxf">3S</mk></mw><gra type="gra" index="8" head="7" relation="PRED"/><mor-post><mw><pos><c>neg</c></pos><stem>not</stem></mw><gra type="gra" index="9" head="8" relation="NEG"/></mor-post></mor></w>
    <w>it<mor type="mor"><mw><pos><c>pro</c><s>per</s></pos><stem>it</stem></mw><gra type="gra" index="10" head="7" relation="PRED"/></mor></w>
    <t type="q"><mor type="mor"><mt type="q"/><gra type="gra" index="11" head="4" relation="PUNCT"/></mor></t>

    <a type="addressee">to T</a>
    <a type="comments">gf works the friction drive to make the bus go Bus goes across floor T runs after it T tries to make the bus "drive"</a>
  </u>
  <u who="MOT" uID="u20">
    <w>give<mor type="mor"><mw><pos><c>v</c></pos><stem>give</stem></mw><gra type="gra" index="1" head="0" relation="ROOT"/></mor></w>
    <w>it<mor type="mor"><mw><pos><c>pro</c><s>per</s></pos><stem>it</stem></mw><gra type="gra" index="2" head="1" relation="OBJ2"/></mor></w>
    <g><w>a<mor type="mor"><mw><pos><c>det</c><s>art</s></pos><stem>a</stem></mw><gra type="gra" index="3" head="4" relation="DET"/></mor></w>
    <w>push<mor type="mor"><mw><pos><c>n</c></pos><stem>push</stem></mw><gra type="gra" index="4" head="1" relation="OBJ"/></mor></w><overlap type="overlap follows"/></g>
    <t type="p"><mor type="mor"><mt type="p"/><gra type="gra" index="5" head="1" relation="PUNCT"/></mor></t>

  </u>
  <u who="MOT" uID="u21">
    <w>and<mor type="mor"><mw><pos><c>coord</c></pos><stem>and</stem></mw><gra type="gra" index="1" head="3" relation="LINK"/></mor></w>
    <w>it<mor type="mor"><mw><pos><c>pro</c><s>per</s></pos><stem>it</stem></mw><gra type="gra" index="2" head="3" relation="SUBJ"/></mor></w>
    <w>goes<mor type="mor"><mw><pos><c>v</c></pos><stem>go</stem><mk type="sfx">3S</mk></mw><gra type="gra" index="3" head="0" relation="ROOT"/></mor></w>
    <t type="p"><mor type="mor"><mt type="p"/><gra type="gra" index="4" head="3" relation="PUNCT"/></mor></t>

  </u>
  <u who="MOT" uID="u22">
    <w>clever<mor type="mor"><mw><pos><c>adj</c></pos><stem>clever</stem></mw><gra type="gra" index="1" head="2" relation="MOD"/></mor></w>
    <w>boy<mor type="mor"><mw><pos><c>n</c></pos><stem>boy</stem></mw><gra type="gra" index="2" head="0" relation="INCROOT"/></mor></w>
    <pause symbolic-length="simple" length="5"/>
    <t type="p"><mor type="mor"><mt type="p"/><gra type="gra" index="3" head="2" relation="PUNCT"/></mor></t>

  </u>
  <u who="MOT" uID="u23">
    <w>he<mor type="mor"><mw><pos><c>pro</c><s>sub</s></pos><stem>he</stem></mw><gra type="gra" index="1" head="2" relation="SUBJ"/></mor></w>
    <w>looks<mor type="mor"><mw><pos><c>cop</c></pos><stem>look</stem><mk type="sfx">3S</mk></mw><gra type="gra" index="2" head="0" relation="ROOT"/></mor></w>
    <w>really<mor type="mor"><mw><pos><c>adv</c></pos><stem>real</stem><mk type="sfxf">dadj</mk><mk type="sfx">LY</mk></mw><gra type="gra" index="3" head="2" relation="JCT"/></mor></w>
    <w>like<mor type="mor"><mw><pos><c>co</c></pos><stem>like</stem></mw><gra type="gra" index="4" head="2" relation="COM"/></mor></w>
    <w>a<mor type="mor"><mw><pos><c>det</c><s>art</s></pos><stem>a</stem></mw><gra type="gra" index="5" head="6" relation="DET"/></mor></w>
    <w>hunchback<mor type="mor"><mw><pos><c>n</c></pos><stem>hunchback</stem></mw><gra type="gra" index="6" head="2" relation="PRED"/></mor></w>
    <w>where<mor type="mor"><mw><pos><c>pro</c><s>rel</s></pos><stem>where</stem></mw><gra type="gra" index="7" head="10" relation="LINK"/></mor></w>
    <w>they've<mor type="mor"><mw><pos><c>pro</c><s>sub</s></pos><stem>they</stem></mw><gra type="gra" index="8" head="10" relation="SUBJ"/><mor-post><mw><pos><c>aux</c></pos><stem>have</stem></mw><gra type="gra" index="9" head="10" relation="AUX"/></mor-post></mor></w>
    <w>put<mor type="mor"><mw><pos><c>part</c></pos><stem>put</stem><mk type="sfxf">PASTP</mk></mw><gra type="gra" index="10" head="6" relation="CMOD"/></mor></w>
    <w>all<mor type="mor"><mw><pos><c>adv</c></pos><stem>all</stem></mw><gra type="gra" index="11" head="12" relation="JCT"/></mor></w>
    <w>these<mor type="mor"><mw><pos><c>det</c><s>dem</s></pos><stem>these</stem></mw><gra type="gra" index="12" head="10" relation="COMP"/></mor></w>
    <w untranscribed="unintelligible">xxx</w>
    <t type="p"><mor type="mor"><mt type="p"/><gra type="gra" index="13" head="2" relation="PUNCT"/></mor></t>

  </u>
  <u who="GRA" uID="u24">
    <w>ax<mor type="mor"><mw><pos><c>n</c></pos><stem>ax</stem></mw><gra type="gra" index="1" head="2" relation="SUBJ"/></mor></w>
    <w>isn't<mor type="mor"><mw><pos><c>cop</c></pos><stem>be</stem><mk type="sfxf">3S</mk></mw><gra type="gra" index="2" head="0" relation="ROOT"/><mor-post><mw><pos><c>neg</c></pos><stem>not</stem></mw><gra type="gra" index="3" head="2" relation="NEG"/></mor-post></mor></w>
    <w>it<mor type="mor"><mw><pos><c>pro</c><s>per</s></pos><stem>it</stem></mw><gra type="gra" index="4" head="2" relation="PRED"/></mor></w>
    <t type="q"><mor type="mor"><mt type="q"/><gra type="gra" index="5" head="2" relation="PUNCT"/></mor></t>

  </u>
  <u who="MOT" uID="u25">
    <w>he<mor type="mor"><mw><pos><c>pro</c><s>sub</s></pos><stem>he</stem></mw><gra type="gra" index="1" head="2" relation="SUBJ"/></mor></w>
    <w>sleeps<mor type="mor"><mw><pos><c>v</c></pos><stem>sleep</stem><mk type="sfx">3S</mk></mw><gra type="gra" index="2" head="0" relation="ROOT"/></mor></w>
    <w>in<mor type="mor"><mw><pos><c>prep</c></pos><stem>in</stem></mw><gra type="gra" index="3" head="2" relation="JCT"/></mor></w>
    <w>it<mor type="mor"><mw><pos><c>pro</c><s>per</s></pos><stem>it</stem></mw><gra type="gra" index="4" head="3" relation="POBJ"/></mor></w>
    <w>yes<mor type="mor"><mw><pos><c>co</c></pos><stem>yes</stem></mw><gra type="gra" index="5" head="2" relation="COM"/></mor></w>
    <t type="p"><mor type="mor"><mt type="p"/><gra type="gra" index="6" head="2" relation="PUNCT"/></mor></t>

    <a type="comments">bus noise</a>
  </u>
  <u who="MOT" uID="u26">
    <w>mind<mor type="mor"><mw><pos><c>v</c></pos><stem>mind</stem></mw><gra type="gra" index="1" head="0" relation="ROOT"/></mor></w>
    <w>you<mor type="mor"><mw><pos><c>pro</c><s>per</s></pos><stem>you</stem></mw><gra type="gra" index="2" head="1" relation="OBJ"/></mor></w>
    <w>it's<mor type="mor"><mw><pos><c>pro</c><s>per</s></pos><stem>it</stem></mw><gra type="gra" index="3" head="4" relation="SUBJ"/><mor-post><mw><pos><c>cop</c></pos><stem>be</stem><mk type="sfxf">3S</mk></mw><gra type="gra" index="4" head="1" relation="COMP"/></mor-post></mor></w>
    <w>pretty<mor type="mor"><mw><pos><c>adj</c></pos><stem>pretty</stem></mw><gra type="gra" index="5" head="4" relation="PRED"/></mor></w>
    <w>well<mor type="mor"><mw><pos><c>adv</c></pos><stem>well</stem></mw><gra type="gra" index="6" head="7" relation="JCT"/></mor></w>
    <w>padded<mor type="mor"><mw><pos><c>part</c></pos><stem>pad</stem><mk type="sfx">PASTP</mk></mw><gra type="gra" index="7" head="4" relation="XJCT"/></mor></w>
    <t type="p"><mor type="mor"><mt type="p"/><gra type="gra" index="8" head="1" relation="PUNCT"/></mor></t>

  </u>
  <comment type="Location">Kitchen</comment>
  <u who="MOT" uID="u27">
    <w>yes<mor type="mor"><mw><pos><c>co</c></pos><stem>yes</stem></mw><gra type="gra" index="1" head="3" relation="COM"/></mor></w>
    <w>it<mor type="mor"><mw><pos><c>pro</c><s>per</s></pos><stem>it</stem></mw><gra type="gra" index="2" head="3" relation="SUBJ"/></mor></w>
    <w>will<mor type="mor"><mw><pos><c>mod</c></pos><stem>will</stem></mw><gra type="gra" index="3" head="0" relation="INCROOT"/></mor></w>
    <t type="p"><mor type="mor"><mt type="p"/><gra type="gra" index="4" head="3" relation="PUNCT"/></mor></t>

  </u>
  <u who="MOT" uID="u28">
    <w>probably<mor type="mor"><mw><pos><c>adv</c></pos><stem>probable</stem><mk type="sfxf">dadj</mk><mk type="sfx">LY</mk></mw><gra type="gra" index="1" head="4" relation="JCT"/></mor></w>
    <w>hafta<mor type="mor"><mw><pos><c>mod</c></pos><stem>have</stem></mw><gra type="gra" index="2" head="4" relation="AUX"/><mor-post><mw><pos><c>inf</c></pos><stem>to</stem></mw><gra type="gra" index="3" head="4" relation="INF"/></mor-post></mor></w>
    <w>lift<mor type="mor"><mw><pos><c>v</c></pos><stem>lift</stem></mw><gra type="gra" index="4" head="0" relation="ROOT"/></mor></w>
    <w>it<mor type="mor"><mw><pos><c>pro</c><s>per</s></pos><stem>it</stem></mw><gra type="gra" index="5" head="4" relation="OBJ"/></mor></w>
    <w>a<mor type="mor"><mw><pos><c>det</c><s>art</s></pos><stem>a</stem></mw><gra type="gra" index="6" head="7" relation="DET"/></mor></w>
    <w>bit<mor type="mor"><mw><pos><c>n</c></pos><stem>bit</stem></mw><gra type="gra" index="7" head="4" relation="OBJ"/></mor></w>
    <w>up<mor type="mor"><mw><pos><c>adv</c></pos><stem>up</stem></mw><gra type="gra" index="8" head="7" relation="NJCT"/></mor></w>
    <w>at<mor type="mor"><mw><pos><c>prep</c></pos><stem>at</stem></mw><gra type="gra" index="9" head="8" relation="JCT"/></mor></w>
    <w>the<mor type="mor"><mw><pos><c>det</c><s>art</s></pos><stem>the</stem></mw><gra type="gra" index="10" head="11" relation="DET"/></mor></w>
    <w>front<mor type="mor"><mw><pos><c>n</c></pos><stem>front</stem></mw><gra type="gra" index="11" head="9" relation="POBJ"/></mor></w>
    <t type="p"><mor type="mor"><mt type="p"/><gra type="gra" index="12" head="4" relation="PUNCT"/></mor></t>

  </u>
  <u who="GRA" uID="u29">
    <w>hold<mor type="mor"><mw><pos><c>n</c></pos><stem>hold</stem></mw><gra type="gra" index="1" head="0" relation="INCROOT"/></mor></w>
    <w>tight<mor type="mor"><mw><pos><c>adv</c></pos><stem>tight</stem></mw><gra type="gra" index="2" head="1" relation="NJCT"/></mor></w>
    <t type="p"><mor type="mor"><mt type="p"/><gra type="gra" index="3" head="1" relation="PUNCT"/></mor></t>

  </u>
  <u who="CHI" uID="u30">
    <g><w>ah<mor type="mor"><mw><pos><c>co</c></pos><stem>ah</stem></mw><gra type="gra" index="1" head="0" relation="INCROOT"/></mor></w><ga type="explanation">yes</ga></g>
    <t type="p"><mor type="mor"><mt type="p"/><gra type="gra" index="2" head="1" relation="PUNCT"/></mor></t>

  </u>
  <u who="GRA" uID="u31">
    <w>yes<mor type="mor"><mw><pos><c>co</c></pos><stem>yes</stem></mw><gra type="gra" index="1" head="0" relation="INCROOT"/></mor></w>
    <t type="p"><mor type="mor"><mt type="p"/><gra type="gra" index="2" head="1" relation="PUNCT"/></mor></t>

  </u>
  <u who="GRA" uID="u32">
    <w>oh<mor type="mor"><mw><pos><c>co</c></pos><stem>oh</stem></mw><gra type="gra" index="1" head="2" relation="COM"/></mor></w>
    <w>dear<mor type="mor"><mw><pos><c>co</c></pos><stem>dear</stem></mw><gra type="gra" index="2" head="0" relation="INCROOT"/></mor></w>
    <t type="p"><mor type="mor"><mt type="p"/><gra type="gra" index="3" head="2" relation="PUNCT"/></mor></t>

  </u>
  <u who="MOT" uID="u33">
    <w>he's<mor type="mor"><mw><pos><c>pro</c><s>sub</s></pos><stem>he</stem></mw><gra type="gra" index="1" head="2" relation="SUBJ"/><mor-post><mw><pos><c>cop</c></pos><stem>be</stem><mk type="sfxf">3S</mk></mw><gra type="gra" index="2" head="0" relation="ROOT"/></mor-post></mor></w>
    <w>a<mor type="mor"><mw><pos><c>det</c><s>art</s></pos><stem>a</stem></mw><gra type="gra" index="3" head="4" relation="DET"/></mor></w>
    <w>bit<mor type="mor"><mw><pos><c>n</c></pos><stem>bit</stem></mw><gra type="gra" index="4" head="2" relation="PRED"/></mor></w>
    <w>late<mor type="mor"><mw><pos><c>adv</c></pos><stem>late</stem></mw><gra type="gra" index="5" head="4" relation="NJCT"/></mor></w>
    <w>this<mor type="mor"><mw><pos><c>det</c><s>dem</s></pos><stem>this</stem></mw><gra type="gra" index="6" head="7" relation="DET"/></mor></w>
    <w>morning<mor type="mor"><mw><pos><c>n</c></pos><stem>morning</stem></mw><gra type="gra" index="7" head="5" relation="POBJ"/></mor></w>
    <t type="p"><mor type="mor"><mt type="p"/><gra type="gra" index="8" head="2" relation="PUNCT"/></mor></t>

  </u>
  <u who="GRA" uID="u34">
    <w>say<mor type="mor"><mw><pos><c>v</c></pos><stem>say</stem></mw><gra type="gra" index="1" head="0" relation="ROOT"/></mor></w>
    <w>hello<mor type="mor"><mw><pos><c>n</c></pos><stem>hello</stem></mw><gra type="gra" index="2" head="1" relation="OBJ"/></mor></w>
    <e><action/></e>
    <t type="p"><mor type="mor"><mt type="p"/><gra type="gra" index="3" head="1" relation="PUNCT"/></mor></t>

  </u>
  <u who="MOT" uID="u35">
    <w>hello<mor type="mor"><mw><pos><c>co</c></pos><stem>hello</stem></mw><gra type="gra" index="1" head="0" relation="INCROOT"/></mor></w>
    <pause symbolic-length="simple" length="3"/>
    <t type="p"><mor type="mor"><mt type="p"/><gra type="gra" index="2" head="1" relation="PUNCT"/></mor></t>

    <a type="comments">answers phone Gf is struggling to put T's bib on</a>
  </u>
  <u who="GRA" uID="u36">
    <w>come<mor type="mor"><mw><pos><c>v</c></pos><stem>come</stem></mw><gra type="gra" index="1" head="0" relation="ROOT"/></mor></w>
    <w>on<mor type="mor"><mw><pos><c>adv</c></pos><stem>on</stem></mw><gra type="gra" index="2" head="1" relation="JCT"/></mor></w>
    <t type="p"><mor type="mor"><mt type="p"/><gra type="gra" index="3" head="1" relation="PUNCT"/></mor></t>

    <a type="paralinguistics">&lt;4.&gt; noises &lt;aft&gt; noise &lt;3.&gt; laughs</a>
  </u>
  <u who="GRA" uID="u37">
    <w>where<mor type="mor"><mw><pos><c>pro</c><s>int</s></pos><stem>where</stem></mw><gra type="gra" index="1" head="0" relation="INCROOT"/></mor></w>
    <w>on<mor type="mor"><mw><pos><c>prep</c></pos><stem>on</stem></mw><gra type="gra" index="2" head="1" relation="JCT"/></mor></w>
    <w>earth<mor type="mor"><mw><pos><c>n</c></pos><stem>earth</stem></mw><gra type="gra" index="3" head="2" relation="POBJ"/></mor></w>
    <pause symbolic-length="simple" length="10"/>
    <t type="trail off"><mor type="mor"><mt type="trail off"/><gra type="gra" index="4" head="1" relation="PUNCT"/></mor></t>

    <a type="comments">gf is trying to get T's thumb out of the sleeve of the bib</a>
  </u>
  <u who="GRA" uID="u38">
    <w>where's<mor type="mor"><mw><pos><c>pro</c><s>int</s></pos><stem>where</stem></mw><gra type="gra" index="1" head="2" relation="SUBJ"/><mor-post><mw><pos><c>cop</c></pos><stem>be</stem><mk type="sfxf">3S</mk></mw><gra type="gra" index="2" head="0" relation="ROOT"/></mor-post></mor></w>
    <w>your<mor type="mor"><mw><pos><c>det</c><s>poss</s></pos><stem>your</stem></mw><gra type="gra" index="3" head="4" relation="DET"/></mor></w>
    <w>thumb<mor type="mor"><mw><pos><c>n</c></pos><stem>thumb</stem></mw><gra type="gra" index="4" head="2" relation="PRED"/></mor></w>
    <t type="p"><mor type="mor"><mt type="p"/><gra type="gra" index="5" head="2" relation="PUNCT"/></mor></t>

    <a type="paralinguistics">sing+song noise</a>
  </u>
  <u who="GRA" uID="u39">
    <e><happening>laughs</happening></e>
    <t type="p"></t>

    <a type="paralinguistics">&lt;aft&gt; cries pretending &lt;aft&gt; sings or moans</a>
  </u>
  <comment type="Time Start">1:21</comment>
  <comment type="Activities">Toilet then free play</comment>
  <comment type="Generic">T is sitting on his pot in the bath+room</comment>
  <u who="MOT" uID="u40">
    <w>let's<mor type="mor"><mw><pos><c>v</c></pos><stem>let</stem></mw><gra type="gra" index="1" head="0" relation="ROOT"/><mor-post><mw><pos><c>pro</c><s>obj</s></pos><stem>us</stem></mw><gra type="gra" index="2" head="1" relation="OBJ"/></mor-post></mor></w>
    <w>just<mor type="mor"><mw><pos><c>adv</c></pos><stem>just</stem></mw><gra type="gra" index="3" head="4" relation="JCT"/></mor></w>
    <g><w>take<mor type="mor"><mw><pos><c>v</c></pos><stem>take</stem></mw><gra type="gra" index="4" head="1" relation="COMP"/></mor></w>
    <w>this<mor type="mor"><mw><pos><c>det</c><s>dem</s></pos><stem>this</stem></mw><gra type="gra" index="5" head="4" relation="OBJ"/></mor></w><overlap type="overlap follows"/></g>
    <t type="p"><mor type="mor"><mt type="p"/><gra type="gra" index="6" head="1" relation="PUNCT"/></mor></t>

  </u>
  <u who="MOT" uID="u41">
    <w>you're<mor type="mor"><mw><pos><c>pro</c><s>per</s></pos><stem>you</stem></mw><gra type="gra" index="1" head="2" relation="SUBJ"/><mor-post><mw><pos><c>cop</c></pos><stem>be</stem><mk type="sfxf">PRES</mk></mw><gra type="gra" index="2" head="0" relation="ROOT"/></mor-post></mor></w>
    <w>straps<mor type="mor"><mw><pos><c>n</c></pos><stem>strap</stem><mk type="sfx">PL</mk></mw><gra type="gra" index="3" head="2" relation="PRED"/></mor></w>
    <w>have<mor type="mor"><mw><pos><c>v</c></pos><stem>have</stem></mw><gra type="gra" index="4" head="2" relation="ENUM"/></mor></w>
    <w>come<mor type="mor"><mw><pos><c>v</c></pos><stem>come</stem></mw><gra type="gra" index="5" head="4" relation="COMP"/></mor></w>
    <w>off<mor type="mor"><mw><pos><c>adv</c></pos><stem>off</stem></mw><gra type="gra" index="6" head="5" relation="JCT"/></mor></w>
    <pause symbolic-length="simple" length="3"/>
    <t type="p"><mor type="mor"><mt type="p"/><gra type="gra" index="7" head="2" relation="PUNCT"/></mor></t>

  </u>
  <u who="MOT" uID="u42">
    <w>stand<mor type="mor"><mw><pos><c>v</c></pos><stem>stand</stem></mw><gra type="gra" index="1" head="0" relation="ROOT"/></mor></w>
    <w>up<mor type="mor"><mw><pos><c>adv</c></pos><stem>up</stem></mw><gra type="gra" index="2" head="1" relation="JCT"/></mor></w>
    <w>then<mor type="mor"><mw><pos><c>adv</c><s>tem</s></pos><stem>then</stem></mw><gra type="gra" index="3" head="2" relation="POBJ"/></mor></w>
    <pause symbolic-length="simple" length="9"/>
    <t type="p"><mor type="mor"><mt type="p"/><gra type="gra" index="4" head="1" relation="PUNCT"/></mor></t>

    <a type="comments">sound of flush being pulled</a>
    <a type="paralinguistics">&lt;aft&gt; noises</a>
  </u>
  <u who="CHI" uID="u43">
    <w type="fragment">mm</w>
    <t type="p"></t>

  </u>
  <u who="MOT" uID="u44">
    <w>o<p type="drawl"/>h<mor type="mor"><mw><pos><c>co</c></pos><stem>oh</stem></mw><gra type="gra" index="1" head="0" relation="INCROOT"/></mor></w>
    <pause symbolic-length="simple" length="3"/>
    <t type="p"><mor type="mor"><mt type="p"/><gra type="gra" index="2" head="1" relation="PUNCT"/></mor></t>

  </u>
  <u who="MOT" uID="u45">
    <w>here<mor type="mor"><mw><pos><c>adv</c></pos><stem>here</stem></mw><gra type="gra" index="1" head="3" relation="JCT"/></mor></w>
    <w>it<mor type="mor"><mw><pos><c>pro</c><s>per</s></pos><stem>it</stem></mw><gra type="gra" index="2" head="3" relation="SUBJ"/></mor></w>
    <w>is<mor type="mor"><mw><pos><c>cop</c></pos><stem>be</stem><mk type="sfxf">3S</mk></mw><gra type="gra" index="3" head="0" relation="ROOT"/></mor></w>
    <t type="p"><mor type="mor"><mt type="p"/><gra type="gra" index="4" head="3" relation="PUNCT"/></mor></t>

  </u>
  <u who="MOT" uID="u46">
    <w>mummie's<mor type="mor"><mw><pos><c>adj</c></pos><stem>mum</stem><mk type="sfxf">dn</mk><mk type="sfx">DIM</mk><mk type="sfx">POSS</mk></mw><gra type="gra" index="1" head="2" relation="SUBJ"/></mor></w>
    <w>got<mor type="mor"><mw><pos><c>v</c></pos><stem>get</stem><mk type="sfxf">PAST</mk></mw><gra type="gra" index="2" head="0" relation="ROOT"/></mor></w>
    <w>it<mor type="mor"><mw><pos><c>pro</c><s>per</s></pos><stem>it</stem></mw><gra type="gra" index="3" head="2" relation="OBJ"/></mor></w>
    <t type="p"><mor type="mor"><mt type="p"/><gra type="gra" index="4" head="2" relation="PUNCT"/></mor></t>

    <a type="comments">m carries T downstairs</a>
  </u>
  <u who="CHI" uID="u47">
    <g><w untranscribed="unintelligible-with-pho">yyy</w><ga type="explanation">hello</ga></g>
    <t type="q"></t>

    <a type="paralinguistics">laughs</a>
  </u>
  <u who="MOT" uID="u48">
    <g><w>hello<mor type="mor"><mw><pos><c>co</c></pos><stem>hello</stem></mw><gra type="gra" index="1" head="0" relation="INCROOT"/></mor></w><overlap type="overlap follows"/></g>
    <t type="p"><mor type="mor"><mt type="p"/><gra type="gra" index="2" head="1" relation="PUNCT"/></mor></t>

  </u>
  <u who="MOT" uID="u49">
    <w>where's<mor type="mor"><mw><pos><c>pro</c><s>int</s></pos><stem>where</stem></mw><gra type="gra" index="1" head="2" relation="SUBJ"/><mor-post><mw><pos><c>cop</c></pos><stem>be</stem><mk type="sfxf">3S</mk></mw><gra type="gra" index="2" head="0" relation="ROOT"/></mor-post></mor></w>
    <w>your<mor type="mor"><mw><pos><c>det</c><s>poss</s></pos><stem>your</stem></mw><gra type="gra" index="3" head="4" relation="DET"/></mor></w>
    <w>wheelbarrow<mor type="mor"><mwc><pos><c>n</c></pos><mw><pos><c>n</c></pos><stem>wheel</stem></mw><mw><pos><c>n</c></pos><stem>barrow</stem></mw></mwc><gra type="gra" index="4" head="2" relation="PRED"/></mor></w>
    <t type="q"><mor type="mor"><mt type="q"/><gra type="gra" index="5" head="2" relation="PUNCT"/></mor></t>

    <a type="comments">they all go into the garden T can be heard pushing the wheelbarrow</a>
  </u>
  <comment type="Time Start">2:07</comment>
  <comment type="Activities">Free play sun+loungers. M is asleep</comment>
  <u who="GRA" uID="u50">
    <w>there<mor type="mor"><mw><pos><c>adv</c></pos><stem>there</stem></mw><gra type="gra" index="1" head="3" relation="JCT"/></mor></w>
    <w>he<mor type="mor"><mw><pos><c>pro</c><s>sub</s></pos><stem>he</stem></mw><gra type="gra" index="2" head="3" relation="SUBJ"/></mor></w>
    <w>goes<mor type="mor"><mw><pos><c>v</c></pos><stem>go</stem><mk type="sfx">3S</mk></mw><gra type="gra" index="3" head="0" relation="ROOT"/></mor></w>
    <pause symbolic-length="simple" length="8"/>
    <t type="p"><mor type="mor"><mt type="p"/><gra type="gra" index="4" head="3" relation="PUNCT"/></mor></t>

  </u>
  <u who="GRA" uID="u51">
    <w>not<mor type="mor"><mw><pos><c>neg</c></pos><stem>not</stem></mw><gra type="gra" index="1" head="0" relation="INCROOT"/></mor></w>
    <w>on<mor type="mor"><mw><pos><c>prep</c></pos><stem>on</stem></mw><gra type="gra" index="2" head="1" relation="JCT"/></mor></w>
    <w>there<mor type="mor"><mw><pos><c>n</c></pos><stem>there</stem></mw><gra type="gra" index="3" head="2" relation="POBJ"/></mor></w>
    <pause symbolic-length="simple" length="7"/>
    <t type="p"><mor type="mor"><mt type="p"/><gra type="gra" index="4" head="1" relation="PUNCT"/></mor></t>

    <a type="comments">t is pushing the bus under the sun beds</a>
  </u>
  <u who="GRA" uID="u52">
    <w>where's<mor type="mor"><mw><pos><c>pro</c><s>int</s></pos><stem>where</stem></mw><gra type="gra" index="1" head="2" relation="SUBJ"/><mor-post><mw><pos><c>cop</c></pos><stem>be</stem><mk type="sfxf">3S</mk></mw><gra type="gra" index="2" head="0" relation="ROOT"/></mor-post></mor></w>
    <w>that<mor type="mor"><mw><pos><c>pro</c><s>dem</s></pos><stem>that</stem></mw><gra type="gra" index="3" head="4" relation="DET"/></mor></w>
    <w>hat<mor type="mor"><mw><pos><c>n</c></pos><stem>hat</stem></mw><gra type="gra" index="4" head="2" relation="PRED"/></mor></w>
    <t type="q"><mor type="mor"><mt type="q"/><gra type="gra" index="5" head="2" relation="PUNCT"/></mor></t>

  </u>
  <u who="CHI" uID="u53">
    <w>oh<mor type="mor"><mw><pos><c>co</c></pos><stem>oh</stem></mw><gra type="gra" index="1" head="0" relation="INCROOT"/></mor></w>
    <t type="p"><mor type="mor"><mt type="p"/><gra type="gra" index="2" head="1" relation="PUNCT"/></mor></t>

    <a type="paralinguistics">&lt;1.&gt; noises &lt;aft&gt; laughs</a>
    <a type="comments">gives Gf the hat T goes back to the bus</a>
  </u>
  <u who="GRA" uID="u54">
    <w>here<mor type="mor"><mw><pos><c>adv</c></pos><stem>here</stem></mw><gra type="gra" index="1" head="3" relation="JCT"/></mor></w>
    <w>you<mor type="mor"><mw><pos><c>pro</c><s>per</s></pos><stem>you</stem></mw><gra type="gra" index="2" head="3" relation="SUBJ"/></mor></w>
    <w>are<mor type="mor"><mw><pos><c>cop</c></pos><stem>be</stem><mk type="sfxf">PRES</mk></mw><gra type="gra" index="3" head="0" relation="ROOT"/></mor></w>
    <w>then<mor type="mor"><mw><pos><c>adv</c><s>tem</s></pos><stem>then</stem></mw><gra type="gra" index="4" head="3" relation="JCT"/></mor></w>
    <t type="p"><mor type="mor"><mt type="p"/><gra type="gra" index="5" head="3" relation="PUNCT"/></mor></t>

    <a type="comments">gf pushes the bus under the sun bed</a>
  </u>
  <u who="GRA" uID="u55">
    <w>it's<mor type="mor"><mw><pos><c>pro</c><s>per</s></pos><stem>it</stem></mw><gra type="gra" index="1" head="3" relation="SUBJ"/><mor-post><mw><pos><c>aux</c></pos><stem>be</stem><mk type="sfxf">3S</mk></mw><gra type="gra" index="2" head="3" relation="AUX"/></mor-post></mor></w>
    <w>gone<mor type="mor"><mw><pos><c>part</c></pos><stem>go</stem><mk type="sfxf">PASTP</mk></mw><gra type="gra" index="3" head="0" relation="ROOT"/></mor></w>
    <w>right<mor type="mor"><mw><pos><c>adv</c></pos><stem>right</stem></mw><gra type="gra" index="4" head="5" relation="JCT"/></mor></w>
    <w>under<mor type="mor"><mw><pos><c>adv</c></pos><stem>under</stem></mw><gra type="gra" index="5" head="3" relation="JCT"/></mor></w>
    <w>Mummy's<mor type="mor"><mw><pos><c>adj</c></pos><stem>Mummy</stem><mk type="sfxf">dn</mk><mk type="sfx">POSS</mk></mw><gra type="gra" index="6" head="7" relation="MOD"/></mor></w>
    <w>chair<mor type="mor"><mw><pos><c>n</c></pos><stem>chair</stem></mw><gra type="gra" index="7" head="5" relation="POBJ"/></mor></w>
    <t type="p"><mor type="mor"><mt type="p"/><gra type="gra" index="8" head="3" relation="PUNCT"/></mor></t>

    <a type="comments">noise of bus being pushed</a>
    <a type="paralinguistics">&lt;aft&gt; bus noise &lt;aft&gt; noises</a>
  </u>
  <comment type="Activities">Free play then resting</comment>
  <u who="MOT" uID="u56">
    <w>oy<mor type="mor"><mw><pos><c>co</c></pos><stem>oy</stem></mw><gra type="gra" index="1" head="0" relation="INCROOT"/></mor></w>
    <t type="p"><mor type="mor"><mt type="p"/><gra type="gra" index="2" head="1" relation="PUNCT"/></mor></t>

    <a type="comments">t is banging his high chair against the wall M tells him not to</a>
  </u>
  <u who="MOT" uID="u57">
    <w>I<mor type="mor"><mw><pos><c>pro</c><s>sub</s></pos><stem>I</stem></mw><gra type="gra" index="1" head="2" relation="SUBJ"/></mor></w>
    <w>think<mor type="mor"><mw><pos><c>v</c></pos><stem>think</stem></mw><gra type="gra" index="2" head="0" relation="ROOT"/></mor></w>
    <w>so<mor type="mor"><mw><pos><c>co</c></pos><stem>so</stem></mw><gra type="gra" index="3" head="4" relation="COM"/></mor></w>
    <w>Daddy<mor type="mor"><mw><pos><c>n</c><s>prop</s></pos><stem>Daddy</stem></mw><gra type="gra" index="4" head="2" relation="OBJ"/></mor></w>
    <t type="p"><mor type="mor"><mt type="p"/><gra type="gra" index="5" head="2" relation="PUNCT"/></mor></t>

  </u>
  <u who="MOT" uID="u58">
    <w>I'm<mor type="mor"><mw><pos><c>pro</c><s>sub</s></pos><stem>I</stem></mw><gra type="gra" index="1" head="3" relation="SUBJ"/><mor-post><mw><pos><c>aux</c></pos><stem>be</stem><mk type="sfxf">1S</mk></mw><gra type="gra" index="2" head="3" relation="AUX"/></mor-post></mor></w>
    <w>going<mor type="mor"><mw><pos><c>part</c></pos><stem>go</stem><mk type="sfx">PRESP</mk></mw><gra type="gra" index="3" head="0" relation="ROOT"/></mor></w>
    <w>to<mor type="mor"><mw><pos><c>inf</c></pos><stem>to</stem></mw><gra type="gra" index="4" head="5" relation="INF"/></mor></w>
    <w>put<mor type="mor"><mw><pos><c>v</c></pos><stem>put</stem><mk type="sfxf">ZERO</mk></mw><gra type="gra" index="5" head="3" relation="COMP"/></mor></w>
    <w>Tony<mor type="mor"><mw><pos><c>n</c><s>prop</s></pos><stem>Tony</stem></mw><gra type="gra" index="6" head="5" relation="OBJ"/></mor></w>
    <w>in<mor type="mor"><mw><pos><c>prep</c></pos><stem>in</stem></mw><gra type="gra" index="7" head="5" relation="JCT"/></mor></w>
    <w>his<mor type="mor"><mw><pos><c>det</c><s>poss</s></pos><stem>his</stem></mw><gra type="gra" index="8" head="9" relation="DET"/></mor></w>
    <w>cot<mor type="mor"><mw><pos><c>n</c></pos><stem>cot</stem></mw><gra type="gra" index="9" head="7" relation="POBJ"/></mor></w>
    <w>for<mor type="mor"><mw><pos><c>prep</c></pos><stem>for</stem></mw><gra type="gra" index="10" head="5" relation="JCT"/></mor></w>
    <w>half<mor type="mor"><mw><pos><c>n</c></pos><stem>half</stem></mw><gra type="gra" index="11" head="10" relation="POBJ"/></mor></w>
    <w>an<mor type="mor"><mw><pos><c>det</c><s>art</s></pos><stem>a</stem></mw><gra type="gra" index="12" head="13" relation="DET"/></mor></w>
    <w>hour<mor type="mor"><mw><pos><c>n</c></pos><stem>hour</stem></mw><gra type="gra" index="13" head="5" relation="OBJ"/></mor></w>
    <w>to<mor type="mor"><mw><pos><c>inf</c></pos><stem>to</stem></mw><gra type="gra" index="14" head="15" relation="INF"/></mor></w>
    <w>read<mor type="mor"><mw><pos><c>v</c></pos><stem>read</stem><mk type="sfxf">ZERO</mk></mw><gra type="gra" index="15" head="13" relation="XMOD"/></mor></w>
    <w>his<mor type="mor"><mw><pos><c>det</c><s>poss</s></pos><stem>his</stem></mw><gra type="gra" index="16" head="17" relation="DET"/></mor></w>
    <w>book<mor type="mor"><mw><pos><c>n</c></pos><stem>book</stem></mw><gra type="gra" index="17" head="15" relation="OBJ"/></mor></w>
    <t type="p"><mor type="mor"><mt type="p"/><gra type="gra" index="18" head="3" relation="PUNCT"/></mor></t>

    <a type="paralinguistics">&lt;aft&gt; sounds of objection &lt;aft&gt; cries</a>
  </u>
  <u who="CHI" uID="u59">
    <w>no<mor type="mor"><mw><pos><c>co</c></pos><stem>no</stem></mw><gra type="gra" index="1" head="2" relation="COM"/></mor></w>
    <w>Mum<mor type="mor"><mw><pos><c>n</c><s>prop</s></pos><stem>Mum</stem></mw><gra type="gra" index="2" head="0" relation="INCROOT"/></mor></w>
    <pause symbolic-length="simple" length="20"/>
    <t type="p"><mor type="mor"><mt type="p"/><gra type="gra" index="3" head="2" relation="PUNCT"/></mor></t>

    <a type="paralinguistics">&lt;3.&gt; noises &lt;aft&gt; cries again</a>
    <a type="comments">m takes T upstairs . Cries when she takes his shoes off . Doesn't want to go to bed</a>
  </u>
  <comment type="Time Start">2:47</comment>
  <comment type="Activities">Resting</comment>
  <u who="CHI" uID="u60">
    <w untranscribed="unintelligible">xxx</w>
    <pause symbolic-length="simple" length="5"/>
    <t type="p"></t>

    <a type="comments">turns pages of his book</a>
  </u>
  <u who="CHI" uID="u61">
    <w>teddy<mor type="mor"><mw><pos><c>n</c></pos><stem>teddy</stem></mw><gra type="gra" index="1" head="0" relation="INCROOT"/></mor></w>
    <t type="p"><mor type="mor"><mt type="p"/><gra type="gra" index="2" head="1" relation="PUNCT"/></mor></t>

  </u>
  <u who="CHI" uID="u62">
    <w>teddy<mor type="mor"><mw><pos><c>n</c></pos><stem>teddy</stem></mw><gra type="gra" index="1" head="0" relation="INCROOT"/></mor></w>
    <t type="p"><mor type="mor"><mt type="p"/><gra type="gra" index="2" head="1" relation="PUNCT"/></mor></t>

    <a type="paralinguistics">&lt;aft&gt; yawns &lt;aft&gt; laughs &lt;aft&gt; sings</a>
  </u>
  <comment type="Location">Nursery</comment>
  <u who="CHI" uID="u63">
    <w untranscribed="unintelligible-with-pho">yyy</w>
    <pause symbolic-length="simple" length="4"/>
    <pause symbolic-length="simple" length="7"/>
    <t type="p"></t>

    <a type="paralinguistics">&lt;aft&gt; laughs</a>
    <a type="comments">laughing at something (noise) in his book</a>
  </u>
  <comment type="Location">Nursery</comment>
  <comment type="Generic">noises and sleepy sound</comment>
  <comment type="Situation">T in his cot almost asleep</comment>
  <comment type="Location">Stairs then kitchen</comment>
  <u who="MOT" uID="u64">
    <w>let's<mor type="mor"><mw><pos><c>v</c></pos><stem>let</stem></mw><gra type="gra" index="1" head="0" relation="ROOT"/><mor-post><mw><pos><c>pro</c><s>obj</s></pos><stem>us</stem></mw><gra type="gra" index="2" head="3" relation="SUBJ"/></mor-post></mor></w>
    <w>go<mor type="mor"><mw><pos><c>v</c></pos><stem>go</stem></mw><gra type="gra" index="3" head="1" relation="COMP"/></mor></w>
    <w>and<mor type="mor"><mw><pos><c>coord</c></pos><stem>and</stem></mw><gra type="gra" index="4" head="3" relation="CONJ"/></mor></w>
    <w>find<mor type="mor"><mw><pos><c>v</c></pos><stem>find</stem></mw><gra type="gra" index="5" head="4" relation="COORD"/></mor></w>
    <w>Daddy<mor type="mor"><mw><pos><c>n</c><s>prop</s></pos><stem>Daddy</stem></mw><gra type="gra" index="6" head="5" relation="OBJ"/></mor></w>
    <t type="p"><mor type="mor"><mt type="p"/><gra type="gra" index="7" head="1" relation="PUNCT"/></mor></t>

  </u>
  <u who="CHI" uID="u65">
    <w>Daddy<mor type="mor"><mw><pos><c>n</c><s>prop</s></pos><stem>Daddy</stem></mw><gra type="gra" index="1" head="0" relation="INCROOT"/></mor></w>
    <t type="p"><mor type="mor"><mt type="p"/><gra type="gra" index="2" head="1" relation="PUNCT"/></mor></t>

    <a type="comments">m starts to lead T down the stairs counting as they come down</a>
  </u>
  <u who="MOT" uID="u66">
    <w>two<mor type="mor"><mw><pos><c>det</c><s>num</s></pos><stem>two</stem></mw><gra type="gra" index="1" head="0" relation="INCROOT"/></mor></w>
    <pause symbolic-length="simple" length="1"/>
    <t type="p"><mor type="mor"><mt type="p"/><gra type="gra" index="2" head="1" relation="PUNCT"/></mor></t>

  </u>
  <u who="CHI" uID="u67">
    <w>Daddy<mor type="mor"><mw><pos><c>n</c><s>prop</s></pos><stem>Daddy</stem></mw><gra type="gra" index="1" head="0" relation="INCROOT"/></mor></w>
    <t type="p"><mor type="mor"><mt type="p"/><gra type="gra" index="2" head="1" relation="PUNCT"/></mor></t>

  </u>
  <u who="FAT" uID="u68">
    <w>yes<mor type="mor"><mw><pos><c>co</c></pos><stem>yes</stem></mw><gra type="gra" index="1" head="0" relation="INCROOT"/></mor></w>
    <t type="p"><mor type="mor"><mt type="p"/><gra type="gra" index="2" head="1" relation="PUNCT"/></mor></t>

  </u>
  <u who="FAT" uID="u69">
    <w>yes<mor type="mor"><mw><pos><c>co</c></pos><stem>yes</stem></mw><gra type="gra" index="1" head="0" relation="INCROOT"/></mor></w>
    <t type="p"><mor type="mor"><mt type="p"/><gra type="gra" index="2" head="1" relation="PUNCT"/></mor></t>

  </u>
  <u who="CHI" uID="u70">
    <w>Daddy<mor type="mor"><mw><pos><c>n</c><s>prop</s></pos><stem>Daddy</stem></mw><gra type="gra" index="1" head="0" relation="INCROOT"/></mor></w>
    <t type="p"><mor type="mor"><mt type="p"/><gra type="gra" index="2" head="1" relation="PUNCT"/></mor></t>

  </u>
  <u who="MOT" uID="u71">
    <w>no<mor type="mor"><mw><pos><c>co</c></pos><stem>no</stem></mw><gra type="gra" index="1" head="0" relation="INCROOT"/></mor></w>
    <t type="p"><mor type="mor"><mt type="p"/><gra type="gra" index="2" head="1" relation="PUNCT"/></mor></t>

    <a type="paralinguistics">&lt;aft&gt; noise</a>
  </u>
  <u who="FAT" uID="u72">
    <w>hello<mor type="mor"><mw><pos><c>co</c></pos><stem>hello</stem></mw><gra type="gra" index="1" head="2" relation="COM"/></mor></w>
    <w>sunshine<mor type="mor"><mw><pos><c>n</c></pos><stem>sunshine</stem></mw><gra type="gra" index="2" head="0" relation="INCROOT"/></mor></w>
    <t type="p"><mor type="mor"><mt type="p"/><gra type="gra" index="3" head="2" relation="PUNCT"/></mor></t>

  </u>
  <u who="FAT" uID="u73">
    <w>don't<mor type="mor"><mw><pos><c>mod</c></pos><stem>do</stem></mw><gra type="gra" index="1" head="3" relation="AUX"/><mor-post><mw><pos><c>neg</c></pos><stem>not</stem></mw><gra type="gra" index="2" head="1" relation="NEG"/></mor-post></mor></w>
    <w>frown<mor type="mor"><mw><pos><c>v</c></pos><stem>frown</stem></mw><gra type="gra" index="3" head="0" relation="ROOT"/></mor></w>
    <t type="p"><mor type="mor"><mt type="p"/><gra type="gra" index="4" head="3" relation="PUNCT"/></mor></t>

  </u>
  <u who="FAT" uID="u74">
    <w>hello<mor type="mor"><mw><pos><c>co</c></pos><stem>hello</stem></mw><gra type="gra" index="1" head="0" relation="INCROOT"/></mor></w>
    <t type="p"><mor type="mor"><mt type="p"/><gra type="gra" index="2" head="1" relation="PUNCT"/></mor></t>

  </u>
  <u who="FAT" uID="u75">
    <w>got<mor type="mor"><mw><pos><c>v</c></pos><stem>get</stem><mk type="sfxf">PAST</mk></mw><gra type="gra" index="1" head="0" relation="ROOT"/></mor></w>
    <w>a<mor type="mor"><mw><pos><c>det</c><s>art</s></pos><stem>a</stem></mw><gra type="gra" index="2" head="3" relation="DET"/></mor></w>
    <w>kiss<mor type="mor"><mw><pos><c>n</c></pos><stem>kiss</stem></mw><gra type="gra" index="3" head="1" relation="OBJ"/></mor></w>
    <w>for<mor type="mor"><mw><pos><c>prep</c></pos><stem>for</stem></mw><gra type="gra" index="4" head="3" relation="NJCT"/></mor></w>
    <w>Daddy<mor type="mor"><mw><pos><c>n</c><s>prop</s></pos><stem>Daddy</stem></mw><gra type="gra" index="5" head="4" relation="POBJ"/></mor></w>
    <t type="q"><mor type="mor"><mt type="q"/><gra type="gra" index="6" head="1" relation="PUNCT"/></mor></t>

  </u>
  <u who="FAT" uID="u76">
    <w>got<mor type="mor"><mw><pos><c>v</c></pos><stem>get</stem><mk type="sfxf">PAST</mk></mw><gra type="gra" index="1" head="0" relation="ROOT"/></mor></w>
    <w>a<mor type="mor"><mw><pos><c>det</c><s>art</s></pos><stem>a</stem></mw><gra type="gra" index="2" head="3" relation="DET"/></mor></w>
    <w>kiss<mor type="mor"><mw><pos><c>n</c></pos><stem>kiss</stem></mw><gra type="gra" index="3" head="1" relation="OBJ"/></mor></w>
    <w>for<mor type="mor"><mw><pos><c>prep</c></pos><stem>for</stem></mw><gra type="gra" index="4" head="3" relation="NJCT"/></mor></w>
    <w>Daddy<mor type="mor"><mw><pos><c>n</c><s>prop</s></pos><stem>Daddy</stem></mw><gra type="gra" index="5" head="4" relation="POBJ"/></mor></w>
    <t type="q"><mor type="mor"><mt type="q"/><gra type="gra" index="6" head="1" relation="PUNCT"/></mor></t>

  </u>
  <u who="FAT" uID="u77">
    <e><happening>laughs</happening></e>
    <t type="p"></t>

  </u>
  <u who="FAT" uID="u78">
    <w>good<mor type="mor"><mw><pos><c>adj</c></pos><stem>good</stem></mw><gra type="gra" index="1" head="2" relation="MOD"/></mor></w>
    <w>boy<mor type="mor"><mw><pos><c>n</c></pos><stem>boy</stem></mw><gra type="gra" index="2" head="4" relation="SUBJ"/></mor></w>
    <w>actually<mor type="mor"><mw><pos><c>adv</c></pos><stem>actual</stem><mk type="sfxf">dadj</mk><mk type="sfx">LY</mk></mw><gra type="gra" index="3" head="4" relation="JCT"/></mor></w>
    <w>got<mor type="mor"><mw><pos><c>v</c></pos><stem>get</stem><mk type="sfxf">PAST</mk></mw><gra type="gra" index="4" head="0" relation="ROOT"/></mor></w>
    <w>a<mor type="mor"><mw><pos><c>det</c><s>art</s></pos><stem>a</stem></mw><gra type="gra" index="5" head="6" relation="DET"/></mor></w>
    <w>kiss<mor type="mor"><mw><pos><c>n</c></pos><stem>kiss</stem></mw><gra type="gra" index="6" head="4" relation="OBJ"/></mor></w>
    <w>from<mor type="mor"><mw><pos><c>prep</c></pos><stem>from</stem></mw><gra type="gra" index="7" head="4" relation="JCT"/></mor></w>
    <w>him<mor type="mor"><mw><pos><c>pro</c><s>obj</s></pos><stem>him</stem></mw><gra type="gra" index="8" head="7" relation="POBJ"/></mor></w>
    <t type="p"><mor type="mor"><mt type="p"/><gra type="gra" index="9" head="4" relation="PUNCT"/></mor></t>

  </u>
  <u who="MOT" uID="u79">
    <w>well<mor type="mor"><mw><pos><c>co</c></pos><stem>well</stem></mw><gra type="gra" index="1" head="2" relation="COM"/></mor></w>
    <w>done<mor type="mor"><mw><pos><c>part</c></pos><stem>do</stem><mk type="sfxf">PASTP</mk></mw><gra type="gra" index="2" head="0" relation="ROOT"/></mor></w>
    <t type="p"><mor type="mor"><mt type="p"/><gra type="gra" index="3" head="2" relation="PUNCT"/></mor></t>

    <a type="comments">kiss noise</a>
  </u>
  <u who="FAT" uID="u80">
    <w>hello<mor type="mor"><mw><pos><c>co</c></pos><stem>hello</stem></mw><gra type="gra" index="1" head="0" relation="INCROOT"/></mor></w>
    <t type="p"><mor type="mor"><mt type="p"/><gra type="gra" index="2" head="1" relation="PUNCT"/></mor></t>

  </u>
  <u who="FAT" uID="u81">
    <w>so<mor type="mor"><mw><pos><c>co</c></pos><stem>so</stem></mw><gra type="gra" index="1" head="4" relation="COM"/></mor></w>
    <w>you<mor type="mor"><mw><pos><c>pro</c><s>per</s></pos><stem>you</stem></mw><gra type="gra" index="2" head="4" relation="SUBJ"/></mor></w>
    <w>were<mor type="mor"><mw><pos><c>aux</c></pos><stem>be</stem><mk type="sfxf">PAST</mk></mw><gra type="gra" index="3" head="4" relation="AUX"/></mor></w>
    <w>saying<mor type="mor"><mw><pos><c>part</c></pos><stem>say</stem><mk type="sfx">PRESP</mk></mw><gra type="gra" index="4" head="0" relation="ROOT"/></mor></w>
    <t type="p"><mor type="mor"><mt type="p"/><gra type="gra" index="5" head="4" relation="PUNCT"/></mor></t>

    <a type="comments">f fetches T's bus</a>
  </u>
  <u who="FAT" uID="u82">
    <w untranscribed="unintelligible">xxx</w>
    <w type="fragment">ov</w>
    <t type="p"></t>

  </u>
  <u who="GRA" uID="u83">
    <w>and<mor type="mor"><mw><pos><c>coord</c></pos><stem>and</stem></mw><gra type="gra" index="1" head="3" relation="LINK"/></mor></w>
    <w>he<mor type="mor"><mw><pos><c>pro</c><s>sub</s></pos><stem>he</stem></mw><gra type="gra" index="2" head="3" relation="SUBJ"/></mor></w>
    <w>picked<mor type="mor"><mw><pos><c>v</c></pos><stem>pick</stem><mk type="sfx">PAST</mk></mw><gra type="gra" index="3" head="0" relation="ROOT"/></mor></w>
    <w>up<mor type="mor"><mw><pos><c>prep</c></pos><stem>up</stem></mw><gra type="gra" index="4" head="3" relation="JCT"/></mor></w>
    <w>these<mor type="mor"><mw><pos><c>det</c><s>dem</s></pos><stem>these</stem></mw><gra type="gra" index="5" head="6" relation="DET"/></mor></w>
    <w>pieces<mor type="mor"><mw><pos><c>n</c></pos><stem>piece</stem><mk type="sfx">PL</mk></mw><gra type="gra" index="6" head="4" relation="POBJ"/></mor></w>
    <w>of<mor type="mor"><mw><pos><c>prep</c></pos><stem>of</stem></mw><gra type="gra" index="7" head="6" relation="NJCT"/></mor></w>
    <w>stone<mor type="mor"><mw><pos><c>n</c></pos><stem>stone</stem></mw><gra type="gra" index="8" head="7" relation="POBJ"/></mor></w>
    <t type="p"><mor type="mor"><mt type="p"/><gra type="gra" index="9" head="3" relation="PUNCT"/></mor></t>

  </u>
  <u who="GRA" uID="u84">
    <w>so<mor type="mor"><mw><pos><c>co</c></pos><stem>so</stem></mw><gra type="gra" index="1" head="3" relation="COM"/></mor></w>
    <w>I<mor type="mor"><mw><pos><c>pro</c><s>sub</s></pos><stem>I</stem></mw><gra type="gra" index="2" head="3" relation="SUBJ"/></mor></w>
    <w>said<mor type="mor"><mw><pos><c>v</c></pos><stem>say</stem><mk type="sfxf">PAST</mk></mw><gra type="gra" index="3" head="0" relation="ROOT"/></mor></w>
    <w>you<mor type="mor"><mw><pos><c>pro</c><s>per</s></pos><stem>you</stem></mw><gra type="gra" index="4" head="7" relation="SUBJ"/></mor></w>
    <w>can't<mor type="mor"><mw><pos><c>mod</c></pos><stem>can</stem></mw><gra type="gra" index="5" head="7" relation="AUX"/><mor-post><mw><pos><c>neg</c></pos><stem>not</stem></mw><gra type="gra" index="6" head="5" relation="NEG"/></mor-post></mor></w>
    <w>get<mor type="mor"><mw><pos><c>v</c></pos><stem>get</stem></mw><gra type="gra" index="7" head="3" relation="COMP"/></mor></w>
    <w>them<mor type="mor"><mw><pos><c>pro</c><s>obj</s></pos><stem>them</stem></mw><gra type="gra" index="8" head="7" relation="OBJ"/></mor></w>
    <w>in<mor type="mor"><mw><pos><c>prep</c></pos><stem>in</stem></mw><gra type="gra" index="9" head="7" relation="JCT"/></mor></w>
    <w>there<mor type="mor"><mw><pos><c>n</c></pos><stem>there</stem></mw><gra type="gra" index="10" head="11" relation="MOD"/></mor></w>
    <w>Tony<mor type="mor"><mw><pos><c>n</c><s>prop</s></pos><stem>Tony</stem></mw><gra type="gra" index="11" head="9" relation="POBJ"/></mor></w>
    <t type="p"><mor type="mor"><mt type="p"/><gra type="gra" index="12" head="3" relation="PUNCT"/></mor></t>

  </u>
  <u who="GRA" uID="u85">
    <w>and<mor type="mor"><mw><pos><c>coord</c></pos><stem>and</stem></mw><gra type="gra" index="1" head="3" relation="LINK"/></mor></w>
    <w>he<mor type="mor"><mw><pos><c>pro</c><s>sub</s></pos><stem>he</stem></mw><gra type="gra" index="2" head="3" relation="SUBJ"/></mor></w>
    <w>went<mor type="mor"><mw><pos><c>v</c></pos><stem>go</stem><mk type="sfxf">PAST</mk></mw><gra type="gra" index="3" head="0" relation="ROOT"/></mor></w>
    <w>straight<mor type="mor"><mw><pos><c>adv</c></pos><stem>straight</stem></mw><gra type="gra" index="4" head="3" relation="JCT"/></mor></w>
    <w>across<mor type="mor"><mw><pos><c>adv</c></pos><stem>across</stem></mw><gra type="gra" index="5" head="3" relation="JCT"/></mor></w>
    <w>to<mor type="mor"><mw><pos><c>prep</c></pos><stem>to</stem></mw><gra type="gra" index="6" head="3" relation="JCT"/></mor></w>
    <w>his<mor type="mor"><mw><pos><c>det</c><s>poss</s></pos><stem>his</stem></mw><gra type="gra" index="7" head="8" relation="DET"/></mor></w>
    <w>wheelbarrow<mor type="mor"><mwc><pos><c>n</c></pos><mw><pos><c>n</c></pos><stem>wheel</stem></mw><mw><pos><c>n</c></pos><stem>barrow</stem></mw></mwc><gra type="gra" index="8" head="6" relation="POBJ"/></mor></w>
    <w>and<mor type="mor"><mw><pos><c>coord</c></pos><stem>and</stem></mw><gra type="gra" index="9" head="3" relation="CONJ"/></mor></w>
    <w>put<mor type="mor"><mw><pos><c>v</c></pos><stem>put</stem><mk type="sfxf">ZERO</mk></mw><gra type="gra" index="10" head="9" relation="COORD"/></mor></w>
    <w>these<mor type="mor"><mw><pos><c>det</c><s>dem</s></pos><stem>these</stem></mw><gra type="gra" index="11" head="12" relation="DET"/></mor></w>
    <w>pieces<mor type="mor"><mw><pos><c>n</c></pos><stem>piece</stem><mk type="sfx">PL</mk></mw><gra type="gra" index="12" head="10" relation="OBJ"/></mor></w>
    <g><w>of<mor type="mor"><mw><pos><c>prep</c></pos><stem>of</stem></mw><gra type="gra" index="13" head="12" relation="NJCT"/></mor></w>
    <w untranscribed="unintelligible">xxx</w><overlap type="overlap follows"/></g>
    <t type="p"><mor type="mor"><mt type="p"/><gra type="gra" index="14" head="3" relation="PUNCT"/></mor></t>

  </u>
  <u who="MOT" uID="u86">
    <w>he's<mor type="mor"><mw><pos><c>pro</c><s>sub</s></pos><stem>he</stem></mw><gra type="gra" index="1" head="2" relation="SUBJ"/><mor-post><mw><pos><c>cop</c></pos><stem>be</stem><mk type="sfxf">3S</mk></mw><gra type="gra" index="2" head="0" relation="ROOT"/></mor-post></mor></w>
    <w>not<mor type="mor"><mw><pos><c>neg</c></pos><stem>not</stem></mw><gra type="gra" index="3" head="2" relation="NEG"/></mor></w>
    <w>as<mor type="mor"><mw><pos><c>prep</c></pos><stem>as</stem></mw><gra type="gra" index="4" head="5" relation="COORD"/></mor></w>
    <w>daft<mor type="mor"><mw><pos><c>adj</c></pos><stem>daft</stem></mw><gra type="gra" index="5" head="2" relation="PRED"/></mor></w>
    <w>as<mor type="mor"><mw><pos><c>prep</c></pos><stem>as</stem></mw><gra type="gra" index="6" head="8" relation="COORD"/></mor></w>
    <w>he<mor type="mor"><mw><pos><c>pro</c><s>sub</s></pos><stem>he</stem></mw><gra type="gra" index="7" head="8" relation="SUBJ"/></mor></w>
    <w>looks<mor type="mor"><mw><pos><c>v</c></pos><stem>look</stem><mk type="sfx">3S</mk></mw><gra type="gra" index="8" head="5" relation="ENUM"/></mor></w>
    <w>either<mor type="mor"><mw><pos><c>adv</c></pos><stem>either</stem></mw><gra type="gra" index="9" head="5" relation="JCT"/></mor></w>
    <g><w untranscribed="unintelligible">xxx</w><overlap type="overlap precedes"/></g>
    <t type="p"><mor type="mor"><mt type="p"/><gra type="gra" index="10" head="2" relation="PUNCT"/></mor></t>

  </u>
  <u who="MOT" uID="u87">
    <pause symbolic-length="simple"/>
    <g><w>a<mor type="mor"><mw><pos><c>det</c><s>art</s></pos><stem>a</stem></mw><gra type="gra" index="1" head="2" relation="DET"/></mor></w>
    <w>hell<mor type="mor"><mw><pos><c>n</c></pos><stem>hell</stem></mw><gra type="gra" index="2" head="10" relation="JCT"/></mor></w><overlap type="overlap precedes"/></g>
    <w>of<mor type="mor"><mw><pos><c>prep</c></pos><stem>of</stem></mw><gra type="gra" index="3" head="2" relation="NJCT"/></mor></w>
    <w>a<mor type="mor"><mw><pos><c>det</c><s>art</s></pos><stem>a</stem></mw><gra type="gra" index="4" head="5" relation="DET"/></mor></w>
    <w>lot<mor type="mor"><mw><pos><c>n</c></pos><stem>lot</stem></mw><gra type="gra" index="5" head="3" relation="POBJ"/></mor></w>
    <w>more<mor type="mor"><mw><pos><c>qn</c></pos><stem>more</stem></mw><gra type="gra" index="6" head="7" relation="QUANT"/></mor></w>
    <w>than<mor type="mor"><mw><pos><c>prep</c></pos><stem>than</stem></mw><gra type="gra" index="7" head="2" relation="NJCT"/></mor></w>
    <w>you<mor type="mor"><mw><pos><c>pro</c><s>per</s></pos><stem>you</stem></mw><gra type="gra" index="8" head="7" relation="POBJ"/></mor></w>
    <w>you<mor type="mor"><mw><pos><c>pro</c><s>per</s></pos><stem>you</stem></mw><gra type="gra" index="9" head="10" relation="SUBJ"/></mor></w>
    <w>know<mor type="mor"><mw><pos><c>v</c></pos><stem>know</stem></mw><gra type="gra" index="10" head="0" relation="ROOT"/></mor></w>
    <w>I<mor type="mor"><mw><pos><c>pro</c><s>sub</s></pos><stem>I</stem></mw><gra type="gra" index="11" head="12" relation="SUBJ"/></mor></w>
    <w>try<mor type="mor"><mw><pos><c>v</c></pos><stem>try</stem></mw><gra type="gra" index="12" head="10" relation="COMP"/></mor></w>
    <w>to<mor type="mor"><mw><pos><c>prep</c></pos><stem>to</stem></mw><gra type="gra" index="13" head="12" relation="JCT"/></mor></w>
    <w untranscribed="unintelligible">xxx</w>
    <w>things<mor type="mor"><mw><pos><c>n</c></pos><stem>thing</stem><mk type="sfx">PL</mk></mw><gra type="gra" index="14" head="13" relation="POBJ"/></mor></w>
    <w>to<mor type="mor"><mw><pos><c>prep</c></pos><stem>to</stem></mw><gra type="gra" index="15" head="12" relation="JCT"/></mor></w>
    <w>him<mor type="mor"><mw><pos><c>pro</c><s>obj</s></pos><stem>him</stem></mw><gra type="gra" index="16" head="15" relation="POBJ"/></mor></w>
    <t type="p"><mor type="mor"><mt type="p"/><gra type="gra" index="17" head="10" relation="PUNCT"/></mor></t>

  </u>
  <u who="FAT" uID="u88">
    <w>he<mor type="mor"><mw><pos><c>pro</c><s>sub</s></pos><stem>he</stem></mw><gra type="gra" index="1" head="2" relation="SUBJ"/></mor></w>
    <w>does<mor type="mor"><mw><pos><c>v</c></pos><stem>do</stem><mk type="sfxf">3S</mk></mw><gra type="gra" index="2" head="0" relation="ROOT"/></mor></w>
    <t type="p"><mor type="mor"><mt type="p"/><gra type="gra" index="3" head="2" relation="PUNCT"/></mor></t>

  </u>
  <u who="FAT" uID="u89">
    <w>he<mor type="mor"><mw><pos><c>pro</c><s>sub</s></pos><stem>he</stem></mw><gra type="gra" index="1" head="2" relation="SUBJ"/></mor></w>
    <w>looks<mor type="mor"><mw><pos><c>v</c></pos><stem>look</stem><mk type="sfx">3S</mk></mw><gra type="gra" index="2" head="0" relation="ROOT"/></mor></w>
    <w>round<mor type="mor"><mw><pos><c>adv</c></pos><stem>round</stem></mw><gra type="gra" index="3" head="2" relation="JCT"/></mor></w>
    <w>at<mor type="mor"><mw><pos><c>prep</c></pos><stem>at</stem></mw><gra type="gra" index="4" head="2" relation="JCT"/></mor></w>
    <w>you<mor type="mor"><mw><pos><c>pro</c><s>per</s></pos><stem>you</stem></mw><gra type="gra" index="5" head="4" relation="POBJ"/></mor></w>
    <t type="p"><mor type="mor"><mt type="p"/><gra type="gra" index="6" head="2" relation="PUNCT"/></mor></t>

  </u>
  <u who="MOT" uID="u90">
    <w>quite<mor type="mor"><mw><pos><c>adv</c></pos><stem>quite</stem></mw><gra type="gra" index="1" head="2" relation="JCT"/></mor></w>
    <w>often<mor type="mor"><mw><pos><c>adv</c></pos><stem>often</stem></mw><gra type="gra" index="2" head="5" relation="JCT"/></mor></w>
    <w>I'll<mor type="mor"><mw><pos><c>pro</c><s>sub</s></pos><stem>I</stem></mw><gra type="gra" index="3" head="5" relation="SUBJ"/><mor-post><mw><pos><c>mod</c></pos><stem>will</stem></mw><gra type="gra" index="4" head="5" relation="AUX"/></mor-post></mor></w>
    <w>say<mor type="mor"><mw><pos><c>v</c></pos><stem>say</stem></mw><gra type="gra" index="5" head="0" relation="ROOT"/></mor></w>
    <w>something<mor type="mor"><mw><pos><c>pro</c><s>indef</s></pos><stem>something</stem></mw><gra type="gra" index="6" head="5" relation="OBJ"/></mor></w>
    <w>to<mor type="mor"><mw><pos><c>inf</c></pos><stem>to</stem></mw><gra type="gra" index="7" head="8" relation="INF"/></mor></w>
    <w>him<mor type="mor"><mw><pos><c>pro</c><s>obj</s></pos><stem>him</stem></mw><gra type="gra" index="8" head="9" relation="SUBJ"/></mor></w>
    <w>Daddy<mor type="mor"><mw><pos><c>n</c><s>prop</s></pos><stem>Daddy</stem></mw><gra type="gra" index="9" head="6" relation="COMP"/></mor></w>
    <t type="p"><mor type="mor"><mt type="p"/><gra type="gra" index="10" head="5" relation="PUNCT"/></mor></t>

  </u>
  <comment type="Location">Kitchen</comment>
  <comment type="Situation">T is playing with his friction drive toy running it on the floor</comment>
  <u who="MOT" uID="u91">
    <w>hello<mor type="mor"><mw><pos><c>co</c></pos><stem>hello</stem></mw><gra type="gra" index="1" head="0" relation="INCROOT"/></mor></w>
    <t type="p"><mor type="mor"><mt type="p"/><gra type="gra" index="2" head="1" relation="PUNCT"/></mor></t>

  </u>
  <u who="CHI" uID="u92">
    <w>hello<mor type="mor"><mw><pos><c>co</c></pos><stem>hello</stem></mw><gra type="gra" index="1" head="0" relation="INCROOT"/></mor></w>
    <t type="p"><mor type="mor"><mt type="p"/><gra type="gra" index="2" head="1" relation="PUNCT"/></mor></t>

  </u>
  <u who="CHI" uID="u93">
    <w>whee<mor type="mor"><mw><pos><c>co</c></pos><stem>whee</stem></mw><gra type="gra" index="1" head="0" relation="INCROOT"/></mor></w>
    <t type="p"><mor type="mor"><mt type="p"/><gra type="gra" index="2" head="1" relation="PUNCT"/></mor></t>

  </u>
  <u who="CHI" uID="u94">
    <w>whee<mor type="mor"><mw><pos><c>co</c></pos><stem>whee</stem></mw><gra type="gra" index="1" head="0" relation="INCROOT"/></mor></w>
    <t type="p"><mor type="mor"><mt type="p"/><gra type="gra" index="2" head="1" relation="PUNCT"/></mor></t>

    <a type="paralinguistics">&lt;aft&gt; laughs</a>
    <a type="comments">echoing T T pushes friction toy up and down and is delving in the toy cupboard T has found a rattle and is shaking it</a>
  </u>
  <comment type="Location">Kitchen</comment>
  <comment type="Generic">gulp</comment>
  <comment type="Situation">Finishing his milk</comment>
  <comment type="Generic">noise Could be "all gone"</comment>
  <u who="CHI" uID="u95">
    <w>all_gone<mor type="mor"><mw><pos><c>co</c></pos><stem>all_gone</stem></mw><gra type="gra" index="1" head="0" relation="INCROOT"/></mor></w>
    <pause symbolic-length="simple" length="9"/>
    <t type="p"><mor type="mor"><mt type="p"/><gra type="gra" index="2" head="1" relation="PUNCT"/></mor></t>

  </u>
  <u who="CHI" uID="u96">
    <w>daddy<mor type="mor"><mw><pos><c>n</c></pos><stem>daddy</stem></mw><gra type="gra" index="1" head="0" relation="INCROOT"/></mor></w>
    <t type="p"><mor type="mor"><mt type="p"/><gra type="gra" index="2" head="1" relation="PUNCT"/></mor></t>

    <a type="paralinguistics">&lt;aft&gt; noise</a>
  </u>
  <comment type="Location">Bathroom/Lounge</comment>
  <comment type="Situation">T is on his pot</comment>
  <u who="MOT" uID="u97">
    <w>let's<mor type="mor"><mw><pos><c>v</c></pos><stem>let</stem></mw><gra type="gra" index="1" head="0" relation="ROOT"/><mor-post><mw><pos><c>pro</c><s>obj</s></pos><stem>us</stem></mw><gra type="gra" index="2" head="1" relation="OBJ"/></mor-post></mor></w>
    <w>see<mor type="mor"><mw><pos><c>v</c></pos><stem>see</stem></mw><gra type="gra" index="3" head="1" relation="COMP"/></mor></w>
    <t type="p"><mor type="mor"><mt type="p"/><gra type="gra" index="4" head="1" relation="PUNCT"/></mor></t>

  </u>
  <u who="MOT" uID="u98">
    <w>you<mor type="mor"><mw><pos><c>pro</c><s>per</s></pos><stem>you</stem></mw><gra type="gra" index="1" head="4" relation="SUBJ"/></mor></w>
    <w>haven't<mor type="mor"><mw><pos><c>aux</c></pos><stem>have</stem></mw><gra type="gra" index="2" head="4" relation="AUX"/><mor-post><mw><pos><c>neg</c></pos><stem>not</stem></mw><gra type="gra" index="3" head="2" relation="NEG"/></mor-post></mor></w>
    <w>have<mor type="mor"><mw><pos><c>v</c></pos><stem>have</stem></mw><gra type="gra" index="4" head="0" relation="ROOT"/></mor></w>
    <w>you<mor type="mor"><mw><pos><c>pro</c><s>per</s></pos><stem>you</stem></mw><gra type="gra" index="5" head="4" relation="OBJ"/></mor></w>
    <t type="q"><mor type="mor"><mt type="q"/><gra type="gra" index="6" head="4" relation="PUNCT"/></mor></t>

  </u>
  <u who="MOT" uID="u99">
    <g><w>don't<mor type="mor"><mw><pos><c>mod</c></pos><stem>do</stem></mw><gra type="gra" index="1" head="3" relation="AUX"/><mor-post><mw><pos><c>neg</c></pos><stem>not</stem></mw><gra type="gra" index="2" head="1" relation="NEG"/></mor-post></mor></w>
    <w>you<mor type="mor"><mw><pos><c>pro</c><s>per</s></pos><stem>you</stem></mw><gra type="gra" index="3" head="0" relation="INCROOT"/></mor></w>
    <pause symbolic-length="simple"/><overlap type="overlap precedes"/><overlap type="overlap follows"/></g>
    <t type="q"><mor type="mor"><mt type="q"/><gra type="gra" index="4" head="3" relation="PUNCT"/></mor></t>

  </u>
  <u who="CHI" uID="u100">
    <g><w>all_gone<mor type="mor"><mw><pos><c>co</c></pos><stem>all_gone</stem></mw><gra type="gra" index="1" head="0" relation="INCROOT"/></mor></w><overlap type="overlap precedes"/><overlap type="overlap follows"/></g>
    <t type="p"><mor type="mor"><mt type="p"/><gra type="gra" index="2" head="1" relation="PUNCT"/></mor></t>

  </u>
  <u who="MOT" uID="u101">
    <g><w>don't<mor type="mor"><mw><pos><c>mod</c></pos><stem>do</stem></mw><gra type="gra" index="1" head="4" relation="AUX"/><mor-post><mw><pos><c>neg</c></pos><stem>not</stem></mw><gra type="gra" index="2" head="1" relation="NEG"/></mor-post></mor></w>
    <w>you<mor type="mor"><mw><pos><c>pro</c><s>per</s></pos><stem>you</stem></mw><gra type="gra" index="3" head="4" relation="SUBJ"/></mor></w>
    <w>wanna<mor type="mor"><mw><pos><c>v</c></pos><stem>want</stem></mw><gra type="gra" index="4" head="0" relation="ROOT"/><mor-post><mw><pos><c>inf</c></pos><stem>to</stem></mw><gra type="gra" index="5" head="6" relation="INF"/></mor-post></mor></w><overlap type="overlap precedes"/></g>
    <w>do<mor type="mor"><mw><pos><c>v</c></pos><stem>do</stem></mw><gra type="gra" index="6" head="4" relation="COMP"/></mor></w>
    <w>a<mor type="mor"><mw><pos><c>det</c><s>art</s></pos><stem>a</stem></mw><gra type="gra" index="7" head="8" relation="DET"/></mor></w>
    <w>wee_wees<mor type="mor"><mw><pos><c>n</c></pos><stem>wee</stem><mk type="sfxf">DUP</mk><mk type="sfx">PL</mk></mw><gra type="gra" index="8" head="6" relation="OBJ"/></mor></w>
    <w>now<mor type="mor"><mw><pos><c>adv</c></pos><stem>now</stem></mw><gra type="gra" index="9" head="6" relation="JCT"/></mor></w>
    <t type="q"><mor type="mor"><mt type="q"/><gra type="gra" index="10" head="4" relation="PUNCT"/></mor></t>

  </u>
  <u who="MOT" uID="u102">
    <w>no<mor type="mor"><mw><pos><c>co</c></pos><stem>no</stem></mw><gra type="gra" index="1" head="0" relation="INCROOT"/></mor></w>
    <t type="q"><mor type="mor"><mt type="q"/><gra type="gra" index="2" head="1" relation="PUNCT"/></mor></t>

  </u>
  <u who="MOT" uID="u103">
    <w>that's<mor type="mor"><mw><pos><c>pro</c><s>dem</s></pos><stem>that</stem></mw><gra type="gra" index="1" head="2" relation="SUBJ"/><mor-post><mw><pos><c>cop</c></pos><stem>be</stem><mk type="sfxf">3S</mk></mw><gra type="gra" index="2" head="0" relation="ROOT"/></mor-post></mor></w>
    <w>a<mor type="mor"><mw><pos><c>det</c><s>art</s></pos><stem>a</stem></mw><gra type="gra" index="3" head="5" relation="DET"/></mor></w>
    <w>toilet<mor type="mor"><mw><pos><c>n</c></pos><stem>toilet</stem></mw><gra type="gra" index="4" head="5" relation="MOD"/></mor></w>
    <w>roll<mor type="mor"><mw><pos><c>n</c></pos><stem>roll</stem></mw><gra type="gra" index="5" head="2" relation="PRED"/></mor></w>
    <t type="p"><mor type="mor"><mt type="p"/><gra type="gra" index="6" head="2" relation="PUNCT"/></mor></t>

    <a type="paralinguistics">&lt;aft&gt; noise</a>
  </u>
  <u who="MOT" uID="u104">
    <g><w untranscribed="unintelligible">xxx</w><overlap type="overlap follows"/></g>
    <w>get<mor type="mor"><mw><pos><c>v</c></pos><stem>get</stem></mw><gra type="gra" index="1" head="0" relation="ROOT"/></mor></w>
    <w>the<mor type="mor"><mw><pos><c>det</c><s>art</s></pos><stem>the</stem></mw><gra type="gra" index="2" head="3" relation="DET"/></mor></w>
    <w untranscribed="unintelligible">xxx</w>
    <w>cut<mor type="mor"><mw><pos><c>n</c></pos><stem>cut</stem></mw><gra type="gra" index="3" head="1" relation="OBJ"/></mor></w>
    <w>off<mor type="mor"><mw><pos><c>prep</c></pos><stem>off</stem></mw><gra type="gra" index="4" head="1" relation="JCT"/></mor></w>
    <w>won't<mor type="mor"><mw><pos><c>mod</c></pos><stem>will</stem></mw><gra type="gra" index="5" head="7" relation="AUX"/><mor-post><mw><pos><c>neg</c></pos><stem>not</stem></mw><gra type="gra" index="6" head="5" relation="NEG"/></mor-post></mor></w>
    <w>you<mor type="mor"><mw><pos><c>pro</c><s>per</s></pos><stem>you</stem></mw><gra type="gra" index="7" head="4" relation="POBJ"/></mor></w>
    <t type="q"><mor type="mor"><mt type="q"/><gra type="gra" index="8" head="1" relation="PUNCT"/></mor></t>

  </u>
  <u who="MOT" uID="u105">
    <w type="filler">eh</w>
    <t type="p"></t>

    <a type="comments">t has a car to play with M picks up T to carry him downstairs</a>
  </u>
  <u who="MOT" uID="u106">
    <w>it's<mor type="mor"><mw><pos><c>pro</c><s>per</s></pos><stem>it</stem></mw><gra type="gra" index="1" head="2" relation="SUBJ"/><mor-post><mw><pos><c>cop</c></pos><stem>be</stem><mk type="sfxf">3S</mk></mw><gra type="gra" index="2" head="0" relation="ROOT"/></mor-post></mor></w>
    <w>one<mor type="mor"><mw><pos><c>det</c><s>num</s></pos><stem>one</stem></mw><gra type="gra" index="3" head="2" relation="PRED"/></mor></w>
    <w>or<mor type="mor"><mw><pos><c>coord</c></pos><stem>or</stem></mw><gra type="gra" index="4" head="3" relation="CONJ"/></mor></w>
    <w>the<mor type="mor"><mw><pos><c>det</c><s>art</s></pos><stem>the</stem></mw><gra type="gra" index="5" head="6" relation="DET"/></mor></w>
    <w>other<mor type="mor"><mw><pos><c>qn</c></pos><stem>other</stem></mw><gra type="gra" index="6" head="4" relation="COORD"/></mor></w>
    <pause symbolic-length="simple" length="2"/>
    <t type="p"><mor type="mor"><mt type="p"/><gra type="gra" index="7" head="2" relation="PUNCT"/></mor></t>

  </u>
  <u who="MOT" uID="u107">
    <w>Alec<mor type="mor"><mw><pos><c>n</c><s>prop</s></pos><stem>Alec</stem></mw><gra type="gra" index="1" head="0" relation="INCROOT"/></mor></w>
    <t type="p"><mor type="mor"><mt type="p"/><gra type="gra" index="2" head="1" relation="PUNCT"/></mor></t>

    <a type="comments">m brings T downtairs TV is on</a>
    <a type="paralinguistics">&lt;aft&gt; noise</a>
  </u>
  <u who="MOT" uID="u108">
    <w>there's<mor type="mor"><mw><pos><c>pro</c><s>exist</s></pos><stem>there</stem></mw><gra type="gra" index="1" head="2" relation="SUBJ"/><mor-post><mw><pos><c>cop</c></pos><stem>be</stem><mk type="sfxf">3S</mk></mw><gra type="gra" index="2" head="0" relation="ROOT"/></mor-post></mor></w>
    <w>Grandpa's<mor type="mor"><mw><pos><c>adj</c></pos><stem>Grandpa</stem><mk type="sfxf">dn</mk><mk type="sfx">POSS</mk></mw><gra type="gra" index="3" head="4" relation="MOD"/></mor></w>
    <w>teeth<mor type="mor"><mw><pos><c>n</c></pos><stem>tooth</stem><mk type="sfxf">PL</mk></mw><gra type="gra" index="4" head="2" relation="PRED"/></mor></w>
    <w>look<mor type="mor"><mw><pos><c>v</c></pos><stem>look</stem></mw><gra type="gra" index="5" head="2" relation="ENUM"/></mor></w>
    <pause symbolic-length="simple" length="3"/>
    <t type="p"><mor type="mor"><mt type="p"/><gra type="gra" index="6" head="2" relation="PUNCT"/></mor></t>

    <a type="comments">whispering</a>
    <a type="paralinguistics">&lt;aft&gt; noise</a>
  </u>
  <u who="GRA" uID="u109">
    <w>oh<mor type="mor"><mw><pos><c>co</c></pos><stem>oh</stem></mw><gra type="gra" index="1" head="0" relation="INCROOT"/></mor></w>
    <t type="p"><mor type="mor"><mt type="p"/><gra type="gra" index="2" head="1" relation="PUNCT"/></mor></t>

  </u>
  <u who="GRA" uID="u110">
    <w>I've<mor type="mor"><mw><pos><c>pro</c><s>sub</s></pos><stem>I</stem></mw><gra type="gra" index="1" head="4" relation="SUBJ"/><mor-post><mw><pos><c>aux</c></pos><stem>have</stem></mw><gra type="gra" index="2" head="4" relation="AUX"/></mor-post></mor></w>
    <w>always<mor type="mor"><mw><pos><c>adv</c></pos><stem>always</stem></mw><gra type="gra" index="3" head="4" relation="JCT"/></mor></w>
    <g><w>wanted<mor type="mor"><mw><pos><c>part</c></pos><stem>want</stem><mk type="sfx">PASTP</mk></mw><gra type="gra" index="4" head="0" relation="ROOT"/></mor></w><overlap type="overlap follows"/></g>
    <w>one<mor type="mor"><mw><pos><c>det</c><s>num</s></pos><stem>one</stem></mw><gra type="gra" index="5" head="4" relation="OBJ"/></mor></w>
    <w>of<mor type="mor"><mw><pos><c>prep</c></pos><stem>of</stem></mw><gra type="gra" index="6" head="5" relation="JCT"/></mor></w>
    <w>those<mor type="mor"><mw><pos><c>pro</c><s>dem</s></pos><stem>those</stem></mw><gra type="gra" index="7" head="6" relation="POBJ"/></mor></w>
    <pause symbolic-length="simple" length="3"/>
    <t type="p"><mor type="mor"><mt type="p"/><gra type="gra" index="8" head="4" relation="PUNCT"/></mor></t>

    <a type="comments">t makes the car run on the floor</a>
  </u>
  <u who="GRA" uID="u111">
    <w>make<mor type="mor"><mw><pos><c>v</c></pos><stem>make</stem></mw><gra type="gra" index="1" head="0" relation="ROOT"/></mor></w>
    <w>it<mor type="mor"><mw><pos><c>pro</c><s>per</s></pos><stem>it</stem></mw><gra type="gra" index="2" head="3" relation="SUBJ"/></mor></w>
    <w>go<mor type="mor"><mw><pos><c>v</c></pos><stem>go</stem></mw><gra type="gra" index="3" head="1" relation="COMP"/></mor></w>
    <pause symbolic-length="simple" length="5"/>
    <t type="p"><mor type="mor"><mt type="p"/><gra type="gra" index="4" head="1" relation="PUNCT"/></mor></t>

  </u>
  <u who="MOT" uID="u112">
    <w>have<mor type="mor"><mw><pos><c>aux</c></pos><stem>have</stem></mw><gra type="gra" index="1" head="3" relation="AUX"/></mor></w>
    <w>you<mor type="mor"><mw><pos><c>pro</c><s>per</s></pos><stem>you</stem></mw><gra type="gra" index="2" head="3" relation="SUBJ"/></mor></w>
    <w>got<mor type="mor"><mw><pos><c>part</c></pos><stem>get</stem><mk type="sfxf">PASTP</mk></mw><gra type="gra" index="3" head="0" relation="ROOT"/></mor></w>
    <w>any<mor type="mor"><mw><pos><c>qn</c></pos><stem>any</stem></mw><gra type="gra" index="4" head="5" relation="QUANT"/></mor></w>
    <w>money<mor type="mor"><mw><pos><c>n</c></pos><stem>money</stem></mw><gra type="gra" index="5" head="3" relation="OBJ"/></mor></w>
    <w>Alec<mor type="mor"><mw><pos><c>n</c><s>prop</s></pos><stem>Alec</stem></mw><gra type="gra" index="6" head="5" relation="APP"/></mor></w>
    <t type="q"><mor type="mor"><mt type="q"/><gra type="gra" index="7" head="3" relation="PUNCT"/></mor></t>

    <a type="comments">tv on T has given Gf the car</a>
  </u>
</CHAT>