<?xml version="1.0" encoding="UTF-8"?>

<CHAT xmlns:xsi="http://www.w3.org/2001/XMLSchema-instance"
      xmlns="http://www.talkbank.org/ns/talkbank"
      xsi:schemaLocation="http://www.talkbank.org/ns/talkbank https://talkbank.org/software/talkbank.xsd"
            DesignType="long"
            ActivityType="toyplay"
            GroupType="TD"
      PID="11312/c-00020306-1"
      Version="2.16.0"
      Lang="eng"
      Corpus="Wells"
      Date="1973-10-24"
      >
  <Participants>
    <participant
      id="CHI"
    name="Rosie"
      role="Target_Child"
      language="eng"
      age="P1Y07M00D"
      sex="female"

    />
    <participant
      id="MOT"
      role="Mother"
      language="eng"
      sex="female"

    />
    <participant
      id="DON"
    name="Donna"
      role="Child"
      language="eng"

    />
    <participant
      id="KEL"
    name="Kelvin"
      role="Child"
      language="eng"

    />
    <participant
      id="GRA"
      role="Grandmother"
      language="eng"

    />
    <participant
      id="MAR"
      role="Unidentified"
      language="eng"

    />
    <participant
      id="UNK"
      role="Unidentified"
      language="eng"

    />
  </Participants>
  <comment type="Situation">Radio on all the time</comment>
  <comment type="Date">24-OCT-1973</comment>
  <comment type="Generic">The recording is very distorted so it is difficult to identify speakers and utterances. Also there is a lack of contextual information.</comment>
  <comment type="Location">Sitting room</comment>
  <comment type="Situation">Radio on all the time</comment>
  <comment type="Generic">&lt;aft&gt; shrieking</comment>
  <comment type="Types">long, toyplay, TD</comment>
  <u who="CHI" uID="u0">
    <w>look<mor type="mor"><mw><pos><c>co</c></pos><stem>look</stem></mw><gra type="gra" index="1" head="0" relation="INCROOT"/></mor></w>
    <pause symbolic-length="simple" length="5"/>
    <t type="p"><mor type="mor"><mt type="p"/><gra type="gra" index="2" head="1" relation="PUNCT"/></mor></t>

  </u>
  <u who="CHI" uID="u1">
    <w>yes<mor type="mor"><mw><pos><c>co</c></pos><stem>yes</stem></mw><gra type="gra" index="1" head="0" relation="INCROOT"/></mor></w>
    <pause symbolic-length="simple" length="13"/>
    <t type="p"><mor type="mor"><mt type="p"/><gra type="gra" index="2" head="1" relation="PUNCT"/></mor></t>

  </u>
  <u who="CHI" uID="u2">
    <w untranscribed="unintelligible">xxx</w>
    <t type="p"></t>

    <a type="paralinguistics">&lt;aft&gt; noise</a>
  </u>
  <comment type="Location">Sitting room</comment>
  <comment type="Situation">Radio on all the time</comment>
  <u who="DON" uID="u3">
    <w>stop<mor type="mor"><mw><pos><c>v</c></pos><stem>stop</stem></mw><gra type="gra" index="1" head="0" relation="ROOT"/></mor></w>
    <w>it<mor type="mor"><mw><pos><c>pro</c><s>per</s></pos><stem>it</stem></mw><gra type="gra" index="2" head="1" relation="OBJ"/></mor></w>
    <t type="p"><mor type="mor"><mt type="p"/><gra type="gra" index="3" head="1" relation="PUNCT"/></mor></t>

    <a type="paralinguistics">&lt;aft&gt; singing &lt;aft&gt; noises</a>
  </u>
  <u who="MOT" uID="u4">
    <w>shut<mor type="mor"><mw><pos><c>v</c></pos><stem>shut</stem><mk type="sfxf">ZERO</mk></mw><gra type="gra" index="1" head="0" relation="ROOT"/></mor></w>
    <w>the<mor type="mor"><mw><pos><c>det</c><s>art</s></pos><stem>the</stem></mw><gra type="gra" index="2" head="3" relation="DET"/></mor></w>
    <w>door<mor type="mor"><mw><pos><c>n</c></pos><stem>door</stem></mw><gra type="gra" index="3" head="1" relation="OBJ"/></mor></w>
    <w>please<mor type="mor"><mw><pos><c>co</c></pos><stem>please</stem></mw><gra type="gra" index="4" head="1" relation="COM"/></mor></w>
    <pause symbolic-length="simple" length="25"/>
    <t type="p"><mor type="mor"><mt type="p"/><gra type="gra" index="5" head="1" relation="PUNCT"/></mor></t>

  </u>
  <comment type="Location">Sitting room</comment>
  <comment type="Situation">R is being nursed D is jealous. Radio is on all the time</comment>
  <u who="CHI" uID="u5">
    <w>Ma<mor type="mor"><mw><pos><c>n</c><s>prop</s></pos><stem>Ma</stem></mw><gra type="gra" index="1" head="0" relation="INCROOT"/></mor></w>
    <t type="p"><mor type="mor"><mt type="p"/><gra type="gra" index="2" head="1" relation="PUNCT"/></mor></t>

  </u>
  <u who="CHI" uID="u6">
    <w untranscribed="unintelligible">xxx</w>
    <pause symbolic-length="simple" length="17"/>
    <t type="p"></t>

  </u>
  <u who="MOT" uID="u7">
    <w>oh<mor type="mor"><mw><pos><c>co</c></pos><stem>oh</stem></mw><gra type="gra" index="1" head="4" relation="COM"/></mor></w>
    <w>don't<mor type="mor"><mw><pos><c>mod</c></pos><stem>do</stem></mw><gra type="gra" index="2" head="4" relation="AUX"/><mor-post><mw><pos><c>neg</c></pos><stem>not</stem></mw><gra type="gra" index="3" head="2" relation="NEG"/></mor-post></mor></w>
    <w>be<mor type="mor"><mw><pos><c>cop</c></pos><stem>be</stem></mw><gra type="gra" index="4" head="0" relation="ROOT"/></mor></w>
    <w>silly<mor type="mor"><mw><pos><c>adj</c></pos><stem>silly</stem></mw><gra type="gra" index="5" head="6" relation="MOD"/></mor></w>
    <w>Don<mor type="mor"><mw><pos><c>n</c><s>prop</s></pos><stem>Don</stem></mw><gra type="gra" index="6" head="4" relation="PRED"/></mor></w>
    <pause symbolic-length="simple" length="5"/>
    <t type="p"><mor type="mor"><mt type="p"/><gra type="gra" index="7" head="4" relation="PUNCT"/></mor></t>

  </u>
  <u who="MOT" uID="u8">
    <w>we've<mor type="mor"><mw><pos><c>pro</c><s>sub</s></pos><stem>we</stem></mw><gra type="gra" index="1" head="3" relation="SUBJ"/><mor-post><mw><pos><c>aux</c></pos><stem>have</stem></mw><gra type="gra" index="2" head="3" relation="AUX"/></mor-post></mor></w>
    <w>got<mor type="mor"><mw><pos><c>part</c></pos><stem>get</stem><mk type="sfxf">PASTP</mk></mw><gra type="gra" index="3" head="0" relation="ROOT"/></mor></w>
    <w>to<mor type="mor"><mw><pos><c>inf</c></pos><stem>to</stem></mw><gra type="gra" index="4" head="5" relation="INF"/></mor></w>
    <w>give<mor type="mor"><mw><pos><c>v</c></pos><stem>give</stem></mw><gra type="gra" index="5" head="3" relation="COMP"/></mor></w>
    <w>you<mor type="mor"><mw><pos><c>pro</c><s>per</s></pos><stem>you</stem></mw><gra type="gra" index="6" head="5" relation="OBJ2"/></mor></w>
    <w>a<mor type="mor"><mw><pos><c>det</c><s>art</s></pos><stem>a</stem></mw><gra type="gra" index="7" head="8" relation="DET"/></mor></w>
    <w>moment<mor type="mor"><mw><pos><c>n</c></pos><stem>moment</stem></mw><gra type="gra" index="8" head="5" relation="OBJ"/></mor></w>
    <pause symbolic-length="simple" length="3"/>
    <t type="p"><mor type="mor"><mt type="p"/><gra type="gra" index="9" head="3" relation="PUNCT"/></mor></t>

  </u>
  <u who="MOT" uID="u9">
    <w>what<mor type="mor"><mw><pos><c>pro</c><s>int</s></pos><stem>what</stem></mw><gra type="gra" index="1" head="4" relation="OBJ"/></mor></w>
    <w>did<mor type="mor"><mw><pos><c>mod</c></pos><stem>do</stem><mk type="sfxf">PAST</mk></mw><gra type="gra" index="2" head="4" relation="AUX"/></mor></w>
    <w>you<mor type="mor"><mw><pos><c>pro</c><s>per</s></pos><stem>you</stem></mw><gra type="gra" index="3" head="4" relation="SUBJ"/></mor></w>
    <w>say<mor type="mor"><mw><pos><c>v</c></pos><stem>say</stem></mw><gra type="gra" index="4" head="0" relation="ROOT"/></mor></w>
    <pause symbolic-length="simple" length="3"/>
    <t type="q"><mor type="mor"><mt type="q"/><gra type="gra" index="5" head="4" relation="PUNCT"/></mor></t>

  </u>
  <u who="DON" uID="u10">
    <w untranscribed="unintelligible">xxx</w>
    <t type="p"></t>

  </u>
  <u who="CHI" uID="u11">
    <w untranscribed="unintelligible">xxx</w>
    <t type="p"></t>

  </u>
  <u who="MOT" uID="u12">
    <w>lift<mor type="mor"><mw><pos><c>v</c></pos><stem>lift</stem></mw><gra type="gra" index="1" head="0" relation="ROOT"/></mor></w>
    <w>your<mor type="mor"><mw><pos><c>det</c><s>poss</s></pos><stem>your</stem></mw><gra type="gra" index="2" head="3" relation="DET"/></mor></w>
    <w>leg<mor type="mor"><mw><pos><c>n</c></pos><stem>leg</stem></mw><gra type="gra" index="3" head="1" relation="OBJ"/></mor></w>
    <w>up<mor type="mor"><mw><pos><c>adv</c></pos><stem>up</stem></mw><gra type="gra" index="4" head="1" relation="JCT"/></mor></w>
    <w>then<mor type="mor"><mw><pos><c>adv</c><s>tem</s></pos><stem>then</stem></mw><gra type="gra" index="5" head="4" relation="POBJ"/></mor></w>
    <pause symbolic-length="simple" length="2"/>
    <t type="p"><mor type="mor"><mt type="p"/><gra type="gra" index="6" head="1" relation="PUNCT"/></mor></t>

  </u>
  <u who="DON" uID="u13">
    <e><happening>laughs</happening></e>
    <t type="p"></t>

    <a type="paralinguistics">&lt;aft&gt; sneezes &lt;aft&gt; noises</a>
  </u>
  <u who="UNK" uID="u14">
    <w untranscribed="unintelligible">xxx</w>
    <pause symbolic-length="simple" length="7"/>
    <t type="p"></t>

  </u>
  <u who="CHI" uID="u15">
    <w untranscribed="unintelligible">xxx</w>
    <pause symbolic-length="simple" length="5"/>
    <t type="p"></t>

  </u>
  <comment type="Location">Sitting room</comment>
  <comment type="Generic">noises</comment>
  <comment type="Situation">R walking around the room</comment>
  <u who="MOT" uID="u16">
    <w untranscribed="unintelligible">xxx</w>
    <pause symbolic-length="simple" length="6"/>
    <t type="p"></t>

  </u>
  <u who="CHI" uID="u17">
    <w>yes<mor type="mor"><mw><pos><c>co</c></pos><stem>yes</stem></mw><gra type="gra" index="1" head="0" relation="INCROOT"/></mor></w>
    <w untranscribed="unintelligible">xxx</w>
    <pause symbolic-length="simple" length="7"/>
    <t type="p"><mor type="mor"><mt type="p"/><gra type="gra" index="2" head="1" relation="PUNCT"/></mor></t>

    <a type="paralinguistics">&lt;aft&gt; noise</a>
  </u>
  <comment type="Location">Sitting room</comment>
  <comment type="Situation">Radio on all the time</comment>
  <u who="GRA" uID="u18">
    <w>no<mor type="mor"><mw><pos><c>co</c></pos><stem>no</stem></mw><gra type="gra" index="1" head="0" relation="INCROOT"/></mor></w>
    <pause symbolic-length="simple" length="12"/>
    <t type="p"><mor type="mor"><mt type="p"/><gra type="gra" index="2" head="1" relation="PUNCT"/></mor></t>

    <a type="comments">children bouncing on the settee</a>
  </u>
  <u who="GRA" uID="u19">
    <w>hey<mor type="mor"><mw><pos><c>co</c></pos><stem>hey</stem></mw><gra type="gra" index="1" head="2" relation="COM"/></mor></w>
    <w>come<mor type="mor"><mw><pos><c>v</c></pos><stem>come</stem></mw><gra type="gra" index="2" head="0" relation="ROOT"/></mor></w>
    <w>here<mor type="mor"><mw><pos><c>adv</c></pos><stem>here</stem></mw><gra type="gra" index="3" head="2" relation="JCT"/></mor></w>
    <pause symbolic-length="simple" length="3"/>
    <t type="p"><mor type="mor"><mt type="p"/><gra type="gra" index="4" head="2" relation="PUNCT"/></mor></t>

  </u>
  <u who="MOT" uID="u20">
    <w>still<mor type="mor"><mw><pos><c>adv</c></pos><stem>still</stem></mw><gra type="gra" index="1" head="2" relation="JCT"/></mor></w>
    <w>working<mor type="mor"><mw><pos><c>part</c></pos><stem>work</stem><mk type="sfx">PRESP</mk></mw><gra type="gra" index="2" head="0" relation="ROOT"/></mor></w>
    <w>down<mor type="mor"><mw><pos><c>prep</c></pos><stem>down</stem></mw><gra type="gra" index="3" head="2" relation="JCT"/></mor></w>
    <w>there<mor type="mor"><mw><pos><c>n</c></pos><stem>there</stem></mw><gra type="gra" index="4" head="3" relation="POBJ"/></mor></w>
    <w>then<mor type="mor"><mw><pos><c>adv</c><s>tem</s></pos><stem>then</stem></mw><gra type="gra" index="5" head="2" relation="JCT"/></mor></w>
    <t type="q"><mor type="mor"><mt type="q"/><gra type="gra" index="6" head="2" relation="PUNCT"/></mor></t>

  </u>
  <u who="GRA" uID="u21">
    <w untranscribed="unintelligible">xxx</w>
    <w>no<mor type="mor"><mw><pos><c>co</c></pos><stem>no</stem></mw><gra type="gra" index="1" head="2" relation="COM"/></mor></w>
    <w>worse<mor type="mor"><mw><pos><c>adj</c></pos><stem>bad</stem><mk type="sfxf">CP</mk></mw><gra type="gra" index="2" head="0" relation="ROOT"/></mor></w>
    <w>up<mor type="mor"><mw><pos><c>prep</c></pos><stem>up</stem></mw><gra type="gra" index="3" head="2" relation="JCT"/></mor></w>
    <w>here<mor type="mor"><mw><pos><c>n</c></pos><stem>here</stem></mw><gra type="gra" index="4" head="3" relation="POBJ"/></mor></w>
    <t type="p"><mor type="mor"><mt type="p"/><gra type="gra" index="5" head="2" relation="PUNCT"/></mor></t>

  </u>
  <u who="GRA" uID="u22">
    <w untranscribed="unintelligible">xxx</w>
    <t type="p"></t>

  </u>
  <u who="MOT" uID="u23">
    <w>yes<mor type="mor"><mw><pos><c>co</c></pos><stem>yes</stem></mw><gra type="gra" index="1" head="0" relation="INCROOT"/></mor></w>
    <w untranscribed="unintelligible">xxx</w>
    <t type="q"><mor type="mor"><mt type="q"/><gra type="gra" index="2" head="1" relation="PUNCT"/></mor></t>

    <a type="paralinguistics">&lt;aft&gt; noises &lt;aft&gt; noises continuously</a>
  </u>
  <u who="GRA" uID="u24">
    <w untranscribed="unintelligible">xxx</w>
    <t type="p"></t>

    <a type="paralinguistics">&lt;aft&gt; noises</a>
    <a type="addressee">to R</a>
    <a type="comments">r and D making noises together</a>
  </u>
  <u who="GRA" uID="u25">
    <w>you<mor type="mor"><mw><pos><c>pro</c><s>per</s></pos><stem>you</stem></mw><gra type="gra" index="1" head="2" relation="SUBJ"/></mor></w>
    <w>have<mor type="mor"><mw><pos><c>v</c></pos><stem>have</stem></mw><gra type="gra" index="2" head="0" relation="ROOT"/></mor></w>
    <w>a<mor type="mor"><mw><pos><c>det</c><s>art</s></pos><stem>a</stem></mw><gra type="gra" index="3" head="4" relation="DET"/></mor></w>
    <w>snack<mor type="mor"><mw><pos><c>n</c></pos><stem>snack</stem></mw><gra type="gra" index="4" head="2" relation="OBJ"/></mor></w>
    <w>with<mor type="mor"><mw><pos><c>prep</c></pos><stem>with</stem></mw><gra type="gra" index="5" head="2" relation="JCT"/></mor></w>
    <w>it<mor type="mor"><mw><pos><c>pro</c><s>per</s></pos><stem>it</stem></mw><gra type="gra" index="6" head="5" relation="POBJ"/></mor></w>
    <t type="p"><mor type="mor"><mt type="p"/><gra type="gra" index="7" head="2" relation="PUNCT"/></mor></t>

  </u>
  <comment type="Location">Sitting room</comment>
  <comment type="Situation">Radio on</comment>
  <comment type="Location">Sitting room</comment>
  <comment type="Situation">R is asleep D is crying box G is looking after the children</comment>
  <u who="DON" uID="u26">
    <w>Mummy<mor type="mor"><mw><pos><c>n</c><s>prop</s></pos><stem>Mummy</stem></mw><gra type="gra" index="1" head="0" relation="INCROOT"/></mor></w>
    <t type="p"><mor type="mor"><mt type="p"/><gra type="gra" index="2" head="1" relation="PUNCT"/></mor></t>

  </u>
  <u who="DON" uID="u27">
    <w>Mumm<mor type="mor"><mw><pos><c>n</c><s>prop</s></pos><stem>Mumm</stem></mw><gra type="gra" index="1" head="0" relation="INCROOT"/></mor></w>
    <t type="p"><mor type="mor"><mt type="p"/><gra type="gra" index="2" head="1" relation="PUNCT"/></mor></t>

  </u>
  <u who="DON" uID="u28">
    <w>Mummy<mor type="mor"><mw><pos><c>n</c><s>prop</s></pos><stem>Mummy</stem></mw><gra type="gra" index="1" head="0" relation="INCROOT"/></mor></w>
    <t type="p"><mor type="mor"><mt type="p"/><gra type="gra" index="2" head="1" relation="PUNCT"/></mor></t>

  </u>
  <u who="DON" uID="u29">
    <w>Mumm<mor type="mor"><mw><pos><c>n</c><s>prop</s></pos><stem>Mumm</stem></mw><gra type="gra" index="1" head="0" relation="INCROOT"/></mor></w>
    <t type="p"><mor type="mor"><mt type="p"/><gra type="gra" index="2" head="1" relation="PUNCT"/></mor></t>

  </u>
  <u who="DON" uID="u30">
    <w>Mummy<mor type="mor"><mw><pos><c>n</c><s>prop</s></pos><stem>Mummy</stem></mw><gra type="gra" index="1" head="0" relation="INCROOT"/></mor></w>
    <t type="p"><mor type="mor"><mt type="p"/><gra type="gra" index="2" head="1" relation="PUNCT"/></mor></t>

  </u>
  <u who="DON" uID="u31">
    <w>Mum<mor type="mor"><mw><pos><c>n</c><s>prop</s></pos><stem>Mum</stem></mw><gra type="gra" index="1" head="0" relation="INCROOT"/></mor></w>
    <t type="p"><mor type="mor"><mt type="p"/><gra type="gra" index="2" head="1" relation="PUNCT"/></mor></t>

  </u>
  <u who="DON" uID="u32">
    <w>Mum<mor type="mor"><mw><pos><c>n</c><s>prop</s></pos><stem>Mum</stem></mw><gra type="gra" index="1" head="0" relation="INCROOT"/></mor></w>
    <t type="p"><mor type="mor"><mt type="p"/><gra type="gra" index="2" head="1" relation="PUNCT"/></mor></t>

  </u>
  <u who="DON" uID="u33">
    <w>Mum<mor type="mor"><mw><pos><c>n</c><s>prop</s></pos><stem>Mum</stem></mw><gra type="gra" index="1" head="0" relation="INCROOT"/></mor></w>
    <t type="p"><mor type="mor"><mt type="p"/><gra type="gra" index="2" head="1" relation="PUNCT"/></mor></t>

  </u>
  <comment type="Time Start">11:47</comment>
  <comment type="Activities">Free play with another child</comment>
  <comment type="Situation">M is getting the lunch Radio is on</comment>
  <u who="DON" uID="u34">
    <w untranscribed="unintelligible-with-pho">yyy</w>
    <pause symbolic-length="simple" length="27"/>
    <t type="p"></t>

    <a type="comments">? playing with paper</a>
  </u>
  <u who="MOT" uID="u35">
    <w>come<mor type="mor"><mw><pos><c>v</c></pos><stem>come</stem></mw><gra type="gra" index="1" head="0" relation="ROOT"/></mor></w>
    <w>on<mor type="mor"><mw><pos><c>adv</c></pos><stem>on</stem></mw><gra type="gra" index="2" head="1" relation="JCT"/></mor></w>
    <w>then<mor type="mor"><mw><pos><c>adv</c><s>tem</s></pos><stem>then</stem></mw><gra type="gra" index="3" head="1" relation="JCT"/></mor></w>
    <pause symbolic-length="simple" length="10"/>
    <t type="p"><mor type="mor"><mt type="p"/><gra type="gra" index="4" head="1" relation="PUNCT"/></mor></t>

    <a type="comments">m has come in from kitchen</a>
  </u>
  <comment type="Location">Sitting room</comment>
  <u who="CHI" uID="u36">
    <w untranscribed="unintelligible-with-pho">yyy</w>
    <t type="p"></t>

  </u>
  <u who="CHI" uID="u37">
    <w untranscribed="unintelligible-with-pho">yyy</w>
    <t type="p"></t>

  </u>
  <u who="CHI" uID="u38">
    <w untranscribed="unintelligible-with-pho">yyy</w>
    <t type="p"></t>

    <a type="comments">d and Ma talking in the background</a>
  </u>
  <u who="MAR" uID="u39">
    <w>who<mor type="mor"><mw><pos><c>pro</c><s>int</s></pos><stem>who</stem></mw><gra type="gra" index="1" head="2" relation="LINK"/></mor></w>
    <w>are<mor type="mor"><mw><pos><c>cop</c></pos><stem>be</stem><mk type="sfxf">PRES</mk></mw><gra type="gra" index="2" head="0" relation="ROOT"/></mor></w>
    <w>they<mor type="mor"><mw><pos><c>pro</c><s>sub</s></pos><stem>they</stem></mw><gra type="gra" index="3" head="2" relation="PRED"/></mor></w>
    <t type="q"><mor type="mor"><mt type="q"/><gra type="gra" index="4" head="2" relation="PUNCT"/></mor></t>

  </u>
  <u who="MAR" uID="u40">
    <w>Janet<mor type="mor"><mw><pos><c>n</c><s>prop</s></pos><stem>Janet</stem></mw><gra type="gra" index="1" head="3" relation="LINK"/></mor></w>
    <w>I<mor type="mor"><mw><pos><c>pro</c><s>sub</s></pos><stem>I</stem></mw><gra type="gra" index="2" head="3" relation="SUBJ"/></mor></w>
    <w>want<mor type="mor"><mw><pos><c>v</c></pos><stem>want</stem></mw><gra type="gra" index="3" head="0" relation="ROOT"/></mor></w>
    <w>those<mor type="mor"><mw><pos><c>det</c><s>dem</s></pos><stem>those</stem></mw><gra type="gra" index="4" head="5" relation="DET"/></mor></w>
    <w>little<mor type="mor"><mw><pos><c>adj</c></pos><stem>little</stem></mw><gra type="gra" index="5" head="3" relation="JCT"/></mor></w>
    <w>there<mor type="mor"><mw><pos><c>adv</c></pos><stem>there</stem></mw><gra type="gra" index="6" head="5" relation="JCT"/></mor></w>
    <t type="p"><mor type="mor"><mt type="p"/><gra type="gra" index="7" head="3" relation="PUNCT"/></mor></t>

  </u>
  <u who="MAR" uID="u41">
    <w>those<mor type="mor"><mw><pos><c>det</c><s>dem</s></pos><stem>those</stem></mw><gra type="gra" index="1" head="3" relation="DET"/></mor></w>
    <w>baby<mor type="mor"><mw><pos><c>n</c></pos><stem>baby</stem></mw><gra type="gra" index="2" head="3" relation="MOD"/></mor></w>
    <w>ones<mor type="mor"><mw><pos><c>pro</c><s>indef</s></pos><stem>one</stem><mk type="sfx">PL</mk></mw><gra type="gra" index="3" head="0" relation="INCROOT"/></mor></w>
    <t type="p"><mor type="mor"><mt type="p"/><gra type="gra" index="4" head="3" relation="PUNCT"/></mor></t>

  </u>
  <comment type="Location">Kitchen</comment>
  <comment type="Situation">M filling up bucket with water for washing</comment>
  <comment type="Generic">&lt;aft&gt; noises</comment>
  <comment type="Location">Sitting room</comment>
  <u who="DON" uID="u42">
    <w untranscribed="unintelligible-with-pho">yyy</w>
    <t type="p"></t>

  </u>
  <u who="DON" uID="u43">
    <w untranscribed="unintelligible-with-pho">yyy</w>
    <t type="p"></t>

    <a type="paralinguistics">noises</a>
  </u>
  <u who="CHI" uID="u44">
    <w>hey<mor type="mor"><mw><pos><c>co</c></pos><stem>hey</stem></mw><gra type="gra" index="1" head="0" relation="INCROOT"/></mor></w>
    <w untranscribed="unintelligible-with-pho">yyy</w>
    <t type="p"><mor type="mor"><mt type="p"/><gra type="gra" index="2" head="1" relation="PUNCT"/></mor></t>

  </u>
  <u who="DON" uID="u45">
    <w>down<mor type="mor"><mw><pos><c>adv</c></pos><stem>down</stem></mw><gra type="gra" index="1" head="0" relation="INCROOT"/></mor></w>
    <t type="p"><mor type="mor"><mt type="p"/><gra type="gra" index="2" head="1" relation="PUNCT"/></mor></t>

    <a type="paralinguistics">noises</a>
  </u>
  <u who="CHI" uID="u46">
    <w untranscribed="unintelligible-with-pho">yyy</w>
    <pause symbolic-length="simple" length="5"/>
    <t type="p"></t>

  </u>
  <u who="CHI" uID="u47">
    <w untranscribed="unintelligible-with-pho">yyy</w>
    <pause symbolic-length="simple" length="2"/>
    <t type="p"></t>

  </u>
  <u who="CHI" uID="u48">
    <w untranscribed="unintelligible-with-pho">yyy</w>
    <t type="p"></t>

    <a type="comments">running about</a>
  </u>
  <u who="CHI" uID="u49">
    <w untranscribed="unintelligible-with-pho">yyy</w>
    <w>yes<mor type="mor"><mw><pos><c>co</c></pos><stem>yes</stem></mw><gra type="gra" index="1" head="0" relation="INCROOT"/></mor></w>
    <t type="p"><mor type="mor"><mt type="p"/><gra type="gra" index="2" head="1" relation="PUNCT"/></mor></t>

  </u>
  <u who="CHI" uID="u50">
    <w>oh<mor type="mor"><mw><pos><c>co</c></pos><stem>oh</stem></mw><gra type="gra" index="1" head="0" relation="INCROOT"/></mor></w>
    <w untranscribed="unintelligible-with-pho">yyy</w>
    <pause symbolic-length="simple" length="3"/>
    <t type="p"><mor type="mor"><mt type="p"/><gra type="gra" index="2" head="1" relation="PUNCT"/></mor></t>

  </u>
  <u who="CHI" uID="u51">
    <w>there<mor type="mor"><mw><pos><c>adv</c></pos><stem>there</stem></mw><gra type="gra" index="1" head="0" relation="INCROOT"/></mor></w>
    <w untranscribed="unintelligible-with-pho">yyy</w>
    <t type="p"><mor type="mor"><mt type="p"/><gra type="gra" index="2" head="1" relation="PUNCT"/></mor></t>

  </u>
  <u who="CHI" uID="u52">
    <w>there<mor type="mor"><mw><pos><c>adv</c></pos><stem>there</stem></mw><gra type="gra" index="1" head="0" relation="INCROOT"/></mor></w>
    <w untranscribed="unintelligible-with-pho">yyy</w>
    <pause symbolic-length="simple" length="7"/>
    <t type="p"><mor type="mor"><mt type="p"/><gra type="gra" index="2" head="1" relation="PUNCT"/></mor></t>

  </u>
  <u who="CHI" uID="u53">
    <w>take<mor type="mor"><mw><pos><c>v</c></pos><stem>take</stem></mw><gra type="gra" index="1" head="0" relation="ROOT"/></mor></w>
    <w>one<mor type="mor"><mw><pos><c>det</c><s>num</s></pos><stem>one</stem></mw><gra type="gra" index="2" head="1" relation="OBJ"/></mor></w>
    <t type="p"><mor type="mor"><mt type="p"/><gra type="gra" index="3" head="1" relation="PUNCT"/></mor></t>

    <a type="paralinguistics">&lt;aft&gt; noises</a>
  </u>
  <u who="MOT" uID="u54">
    <w>do<mor type="mor"><mw><pos><c>mod</c></pos><stem>do</stem></mw><gra type="gra" index="1" head="3" relation="AUX"/></mor></w>
    <w>you<mor type="mor"><mw><pos><c>pro</c><s>per</s></pos><stem>you</stem></mw><gra type="gra" index="2" head="3" relation="SUBJ"/></mor></w>
    <w>want<mor type="mor"><mw><pos><c>v</c></pos><stem>want</stem></mw><gra type="gra" index="3" head="0" relation="ROOT"/></mor></w>
    <w>a<mor type="mor"><mw><pos><c>det</c><s>art</s></pos><stem>a</stem></mw><gra type="gra" index="4" head="5" relation="DET"/></mor></w>
    <w>smack<mor type="mor"><mw><pos><c>v</c></pos><stem>smack</stem></mw><gra type="gra" index="5" head="3" relation="OBJ"/></mor></w>
    <t type="q"><mor type="mor"><mt type="q"/><gra type="gra" index="6" head="3" relation="PUNCT"/></mor></t>

  </u>
  <u who="CHI" uID="u55">
    <w>what<mor type="mor"><mw><pos><c>pro</c><s>int</s></pos><stem>what</stem></mw><gra type="gra" index="1" head="0" relation="INCROOT"/></mor></w>
    <pause symbolic-length="simple" length="4"/>
    <t type="q"><mor type="mor"><mt type="q"/><gra type="gra" index="2" head="1" relation="PUNCT"/></mor></t>

  </u>
  <comment type="Location">Sitting room</comment>
  <comment type="Situation">M washing TV on D tickling R on the tummy</comment>
  <u who="DON" uID="u56">
    <e><happening>laughs</happening></e>
    <t type="p"></t>

    <a type="paralinguistics">&lt;aft&gt; intermittent laughter</a>
  </u>
  <u who="CHI" uID="u57">
    <w>yes<mor type="mor"><mw><pos><c>co</c></pos><stem>yes</stem></mw><gra type="gra" index="1" head="0" relation="INCROOT"/></mor></w>
    <pause symbolic-length="simple" length="5"/>
    <t type="p"><mor type="mor"><mt type="p"/><gra type="gra" index="2" head="1" relation="PUNCT"/></mor></t>

  </u>
  <u who="DON" uID="u58">
    <w>wee<mor type="mor"><mw><pos><c>n</c></pos><stem>wee</stem></mw><gra type="gra" index="1" head="0" relation="INCROOT"/></mor></w>
    <w>too<mor type="mor"><mw><pos><c>adv</c></pos><stem>too</stem></mw><gra type="gra" index="2" head="3" relation="JCT"/></mor></w>
    <w>late<mor type="mor"><mw><pos><c>adv</c></pos><stem>late</stem></mw><gra type="gra" index="3" head="1" relation="NJCT"/></mor></w>
    <t type="p"><mor type="mor"><mt type="p"/><gra type="gra" index="4" head="1" relation="PUNCT"/></mor></t>

  </u>
  <u who="DON" uID="u59">
    <w untranscribed="unintelligible">xxx</w>
    <pause symbolic-length="simple" length="5"/>
    <t type="p"></t>

  </u>
  <comment type="Location">Sitting room</comment>
  <comment type="Generic">coughing &lt;aft&gt; screams</comment>
  <comment type="Situation">Record player on throughout M in the kitchen finishing the washing</comment>
  <u who="DON" uID="u60">
    <w>down<mor type="mor"><mw><pos><c>adv</c></pos><stem>down</stem></mw><gra type="gra" index="1" head="0" relation="INCROOT"/></mor></w>
    <t type="p"><mor type="mor"><mt type="p"/><gra type="gra" index="2" head="1" relation="PUNCT"/></mor></t>

    <a type="paralinguistics">laughing</a>
  </u>
  <comment type="Time Start">2:07</comment>
  <comment type="Activities">Free play with another child</comment>
  <comment type="Situation">M in kitchen R and D still have the record player on</comment>
  <u who="DON" uID="u61">
    <w>I'm<mor type="mor"><mw><pos><c>pro</c><s>sub</s></pos><stem>I</stem></mw><gra type="gra" index="1" head="3" relation="SUBJ"/><mor-post><mw><pos><c>aux</c></pos><stem>be</stem><mk type="sfxf">1S</mk></mw><gra type="gra" index="2" head="3" relation="AUX"/></mor-post></mor></w>
    <w>going<mor type="mor"><mw><pos><c>part</c></pos><stem>go</stem><mk type="sfx">PRESP</mk></mw><gra type="gra" index="3" head="0" relation="ROOT"/></mor></w>
    <w>to<mor type="mor"><mw><pos><c>inf</c></pos><stem>to</stem></mw><gra type="gra" index="4" head="5" relation="INF"/></mor></w>
    <w>be<mor type="mor"><mw><pos><c>cop</c></pos><stem>be</stem></mw><gra type="gra" index="5" head="3" relation="COMP"/></mor></w>
    <w>sick<mor type="mor"><mw><pos><c>adj</c></pos><stem>sick</stem></mw><gra type="gra" index="6" head="5" relation="PRED"/></mor></w>
    <pause symbolic-length="simple" length="13"/>
    <t type="p"><mor type="mor"><mt type="p"/><gra type="gra" index="7" head="3" relation="PUNCT"/></mor></t>

    <a type="paralinguistics">&lt;aft&gt; noises &lt;aft&gt; noises</a>
  </u>
  <comment type="Time Start">2:35</comment>
  <comment type="Activities">Physical comforting</comment>
  <u who="DON" uID="u62">
    <w>isn't<mor type="mor"><mw><pos><c>cop</c></pos><stem>be</stem><mk type="sfxf">3S</mk></mw><gra type="gra" index="1" head="0" relation="ROOT"/><mor-post><mw><pos><c>neg</c></pos><stem>not</stem></mw><gra type="gra" index="2" head="1" relation="NEG"/></mor-post></mor></w>
    <t type="p"><mor type="mor"><mt type="p"/><gra type="gra" index="3" head="1" relation="PUNCT"/></mor></t>

  </u>
  <u who="DON" uID="u63">
    <w>it<mor type="mor"><mw><pos><c>pro</c><s>per</s></pos><stem>it</stem></mw><gra type="gra" index="1" head="2" relation="SUBJ"/></mor></w>
    <w>is<mor type="mor"><mw><pos><c>cop</c></pos><stem>be</stem><mk type="sfxf">3S</mk></mw><gra type="gra" index="2" head="0" relation="ROOT"/></mor></w>
    <t type="p"><mor type="mor"><mt type="p"/><gra type="gra" index="3" head="2" relation="PUNCT"/></mor></t>

    <a type="comments">record put on</a>
  </u>
  <u who="MOT" uID="u64">
    <w>look<mor type="mor"><mw><pos><c>co</c></pos><stem>look</stem></mw><gra type="gra" index="1" head="0" relation="INCROOT"/></mor></w>
    <t type="p"><mor type="mor"><mt type="p"/><gra type="gra" index="2" head="1" relation="PUNCT"/></mor></t>

  </u>
  <u who="MOT" uID="u65">
    <w untranscribed="unintelligible">xxx</w>
    <pause symbolic-length="simple" length="3"/>
    <t type="p"></t>

  </u>
  <u who="MOT" uID="u66">
    <w>yes<mor type="mor"><mw><pos><c>co</c></pos><stem>yes</stem></mw><gra type="gra" index="1" head="0" relation="INCROOT"/></mor></w>
    <pause symbolic-length="simple" length="48"/>
    <t type="p"><mor type="mor"><mt type="p"/><gra type="gra" index="2" head="1" relation="PUNCT"/></mor></t>

  </u>
  <u who="CHI" uID="u67">
    <w untranscribed="unintelligible">xxx</w>
    <t type="p"></t>

  </u>
  <u who="MOT" uID="u68">
    <w>night<mor type="mor"><mw><pos><c>n</c></pos><stem>night</stem></mw><gra type="gra" index="1" head="2" relation="MOD"/></mor></w>
    <w>night<mor type="mor"><mw><pos><c>n</c></pos><stem>night</stem></mw><gra type="gra" index="2" head="0" relation="INCROOT"/></mor></w>
    <t type="p"><mor type="mor"><mt type="p"/><gra type="gra" index="3" head="2" relation="PUNCT"/></mor></t>

  </u>
  <u who="MOT" uID="u69">
    <w>what<mor type="mor"><mw><pos><c>pro</c><s>int</s></pos><stem>what</stem></mw><gra type="gra" index="1" head="0" relation="INCROOT"/></mor></w>
    <t type="q"><mor type="mor"><mt type="q"/><gra type="gra" index="2" head="1" relation="PUNCT"/></mor></t>

    <a type="comments">father has gone away</a>
  </u>
  <u who="GRA" uID="u70">
    <w>yes<mor type="mor"><mw><pos><c>co</c></pos><stem>yes</stem></mw><gra type="gra" index="1" head="0" relation="INCROOT"/></mor></w>
    <t type="p"><mor type="mor"><mt type="p"/><gra type="gra" index="2" head="1" relation="PUNCT"/></mor></t>

  </u>
  <u who="GRA" uID="u71">
    <w untranscribed="unintelligible">xxx</w>
    <t type="p"></t>

  </u>
  <comment type="Location">Sitting room</comment>
  <comment type="Situation">M has R on her lap as she is trying to get her off to sleep</comment>
  <u who="GRA" uID="u72">
    <w type="filler">eh</w>
    <t type="q"></t>

  </u>
  <u who="GRA" uID="u73">
    <w>oh<mor type="mor"><mw><pos><c>co</c></pos><stem>oh</stem></mw><gra type="gra" index="1" head="0" relation="INCROOT"/></mor></w>
    <t type="p"><mor type="mor"><mt type="p"/><gra type="gra" index="2" head="1" relation="PUNCT"/></mor></t>

  </u>
  <u who="MOT" uID="u74">
    <w>he<mor type="mor"><mw><pos><c>pro</c><s>sub</s></pos><stem>he</stem></mw><gra type="gra" index="1" head="2" relation="SUBJ"/></mor></w>
    <w>said<mor type="mor"><mw><pos><c>v</c></pos><stem>say</stem><mk type="sfxf">PAST</mk></mw><gra type="gra" index="2" head="0" relation="ROOT"/></mor></w>
    <w>it<mor type="mor"><mw><pos><c>pro</c><s>per</s></pos><stem>it</stem></mw><gra type="gra" index="3" head="4" relation="SUBJ"/></mor></w>
    <w>works<mor type="mor"><mw><pos><c>n</c></pos><stem>work</stem><mk type="sfx">PL</mk></mw><gra type="gra" index="4" head="2" relation="OBJ"/></mor></w>
    <w>as<mor type="mor"><mw><pos><c>adv</c></pos><stem>as</stem></mw><gra type="gra" index="5" head="6" relation="COORD"/></mor></w>
    <w>far<mor type="mor"><mw><pos><c>adv</c></pos><stem>far</stem></mw><gra type="gra" index="6" head="4" relation="NJCT"/></mor></w>
    <w>as<mor type="mor"><mw><pos><c>conj</c></pos><stem>as</stem></mw><gra type="gra" index="7" head="9" relation="COORD"/></mor></w>
    <w>the<mor type="mor"><mw><pos><c>det</c><s>art</s></pos><stem>the</stem></mw><gra type="gra" index="8" head="9" relation="DET"/></mor></w>
    <w>garages<mor type="mor"><mw><pos><c>n</c></pos><stem>garage</stem><mk type="sfx">PL</mk></mw><gra type="gra" index="9" head="6" relation="ENUM"/></mor></w>
    <t type="p"><mor type="mor"><mt type="p"/><gra type="gra" index="10" head="2" relation="PUNCT"/></mor></t>

  </u>
  <u who="MOT" uID="u75">
    <w>if<mor type="mor"><mw><pos><c>conj</c></pos><stem>if</stem></mw><gra type="gra" index="1" head="3" relation="LINK"/></mor></w>
    <w>I<mor type="mor"><mw><pos><c>pro</c><s>sub</s></pos><stem>I</stem></mw><gra type="gra" index="2" head="3" relation="SUBJ"/></mor></w>
    <w>went<mor type="mor"><mw><pos><c>v</c></pos><stem>go</stem><mk type="sfxf">PAST</mk></mw><gra type="gra" index="3" head="0" relation="ROOT"/></mor></w>
    <w>further<mor type="mor"><mw><pos><c>adv</c></pos><stem>further</stem></mw><gra type="gra" index="4" head="3" relation="JCT"/></mor></w>
    <w>than<mor type="mor"><mw><pos><c>prep</c></pos><stem>than</stem></mw><gra type="gra" index="5" head="3" relation="JCT"/></mor></w>
    <w>that<mor type="mor"><mw><pos><c>pro</c><s>dem</s></pos><stem>that</stem></mw><gra type="gra" index="6" head="5" relation="POBJ"/></mor></w>
    <t type="p"><mor type="mor"><mt type="p"/><gra type="gra" index="7" head="3" relation="PUNCT"/></mor></t>

  </u>
  <u who="GRA" uID="u76">
    <w>it's<mor type="mor"><mw><pos><c>pro</c><s>per</s></pos><stem>it</stem></mw><gra type="gra" index="1" head="2" relation="SUBJ"/><mor-post><mw><pos><c>cop</c></pos><stem>be</stem><mk type="sfxf">3S</mk></mw><gra type="gra" index="2" head="0" relation="ROOT"/></mor-post></mor></w>
    <w>a<mor type="mor"><mw><pos><c>det</c><s>art</s></pos><stem>a</stem></mw><gra type="gra" index="3" head="4" relation="DET"/></mor></w>
    <w>way<mor type="mor"><mw><pos><c>n</c></pos><stem>way</stem></mw><gra type="gra" index="4" head="2" relation="PRED"/></mor></w>
    <w>out<mor type="mor"><mw><pos><c>adv</c></pos><stem>out</stem></mw><gra type="gra" index="5" head="4" relation="NJCT"/></mor></w>
    <w>bloody<mor type="mor"><mw><pos><c>adj</c></pos><stem>blood</stem><mk type="sfxf">dn</mk><mk type="sfx">Y</mk></mw><gra type="gra" index="6" head="7" relation="MOD"/></mor></w>
    <w>way<mor type="mor"><mw><pos><c>n</c></pos><stem>way</stem></mw><gra type="gra" index="7" head="5" relation="POBJ"/></mor></w>
    <w>if<mor type="mor"><mw><pos><c>conj</c></pos><stem>if</stem></mw><gra type="gra" index="8" head="12" relation="LINK"/></mor></w>
    <w>it<mor type="mor"><mw><pos><c>pro</c><s>per</s></pos><stem>it</stem></mw><gra type="gra" index="9" head="12" relation="SUBJ"/></mor></w>
    <w>doesn't<mor type="mor"><mw><pos><c>mod</c></pos><stem>do</stem><mk type="sfxf">3S</mk></mw><gra type="gra" index="10" head="12" relation="AUX"/><mor-post><mw><pos><c>neg</c></pos><stem>not</stem></mw><gra type="gra" index="11" head="10" relation="NEG"/></mor-post></mor></w>
    <w>work<mor type="mor"><mw><pos><c>n</c></pos><stem>work</stem></mw><gra type="gra" index="12" head="2" relation="CJCT"/></mor></w>
    <t type="p"><mor type="mor"><mt type="p"/><gra type="gra" index="13" head="2" relation="PUNCT"/></mor></t>

  </u>
  <u who="MOT" uID="u77">
    <w>come<mor type="mor"><mw><pos><c>v</c></pos><stem>come</stem></mw><gra type="gra" index="1" head="0" relation="ROOT"/></mor></w>
    <w>here<mor type="mor"><mw><pos><c>adv</c></pos><stem>here</stem></mw><gra type="gra" index="2" head="1" relation="JCT"/></mor></w>
    <t type="p"><mor type="mor"><mt type="p"/><gra type="gra" index="3" head="1" relation="PUNCT"/></mor></t>

  </u>
  <u who="DON" uID="u78">
    <w>I'm<mor type="mor"><mw><pos><c>pro</c><s>sub</s></pos><stem>I</stem></mw><gra type="gra" index="1" head="2" relation="SUBJ"/><mor-post><mw><pos><c>cop</c></pos><stem>be</stem><mk type="sfxf">1S</mk></mw><gra type="gra" index="2" head="0" relation="ROOT"/></mor-post></mor></w>
    <w untranscribed="unintelligible">xxx</w>
    <t type="p"><mor type="mor"><mt type="p"/><gra type="gra" index="3" head="2" relation="PUNCT"/></mor></t>

  </u>
  <u who="DON" uID="u79">
    <w untranscribed="unintelligible">xxx</w>
    <t type="p"></t>

  </u>
  <u who="MOT" uID="u80">
    <w untranscribed="unintelligible">xxx</w>
    <t type="p"></t>

  </u>
  <u who="MOT" uID="u81">
    <w untranscribed="unintelligible">xxx</w>
    <w>out<mor type="mor"><mw><pos><c>adv</c></pos><stem>out</stem></mw><gra type="gra" index="1" head="0" relation="INCROOT"/></mor></w>
    <w>and<mor type="mor"><mw><pos><c>coord</c></pos><stem>and</stem></mw><gra type="gra" index="2" head="1" relation="CONJ"/></mor></w>
    <w>tell<mor type="mor"><mw><pos><c>v</c></pos><stem>tell</stem></mw><gra type="gra" index="3" head="2" relation="COORD"/></mor></w>
    <w>me<mor type="mor"><mw><pos><c>pro</c><s>obj</s></pos><stem>me</stem></mw><gra type="gra" index="4" head="3" relation="OBJ2"/></mor></w>
    <w>when<mor type="mor"><mw><pos><c>pro</c><s>rel</s></pos><stem>when</stem></mw><gra type="gra" index="5" head="8" relation="LINK"/></mor></w>
    <w>you're<mor type="mor"><mw><pos><c>pro</c><s>per</s></pos><stem>you</stem></mw><gra type="gra" index="6" head="8" relation="SUBJ"/><mor-post><mw><pos><c>aux</c></pos><stem>be</stem><mk type="sfxf">PRES</mk></mw><gra type="gra" index="7" head="8" relation="AUX"/></mor-post></mor></w>
    <w>coming<mor type="mor"><mw><pos><c>part</c></pos><stem>come</stem><mk type="sfx">PRESP</mk></mw><gra type="gra" index="8" head="3" relation="COMP"/></mor></w>
    <w>in<mor type="mor"><mw><pos><c>adv</c></pos><stem>in</stem></mw><gra type="gra" index="9" head="8" relation="JCT"/></mor></w>
    <pause symbolic-length="simple" length="5"/>
    <t type="p"><mor type="mor"><mt type="p"/><gra type="gra" index="10" head="1" relation="PUNCT"/></mor></t>

    <a type="addressee">to R</a>
  </u>
  <u who="GRA" uID="u82">
    <w>she's<mor type="mor"><mw><pos><c>pro</c><s>sub</s></pos><stem>she</stem></mw><gra type="gra" index="1" head="2" relation="SUBJ"/><mor-post><mw><pos><c>cop</c></pos><stem>be</stem><mk type="sfxf">3S</mk></mw><gra type="gra" index="2" head="0" relation="ROOT"/></mor-post></mor></w>
    <w>dead<mor type="mor"><mw><pos><c>adj</c></pos><stem>dead</stem></mw><gra type="gra" index="3" head="2" relation="PRED"/></mor></w>
    <w>tired<mor type="mor"><mw><pos><c>part</c></pos><stem>tire</stem><mk type="sfx">PASTP</mk></mw><gra type="gra" index="4" head="3" relation="XMOD"/></mor></w>
    <t type="p"><mor type="mor"><mt type="p"/><gra type="gra" index="5" head="2" relation="PUNCT"/></mor></t>

    <a type="addressee">to R</a>
  </u>
  <u who="MOT" uID="u83">
    <w>yes<mor type="mor"><mw><pos><c>co</c></pos><stem>yes</stem></mw><gra type="gra" index="1" head="0" relation="INCROOT"/></mor></w>
    <t type="p"><mor type="mor"><mt type="p"/><gra type="gra" index="2" head="1" relation="PUNCT"/></mor></t>

  </u>
  <comment type="Location">Sitting room</comment>
  <comment type="Situation">Record player on throughout</comment>
  <u who="MOT" uID="u84">
    <w>don't<mor type="mor"><mw><pos><c>mod</c></pos><stem>do</stem></mw><gra type="gra" index="1" head="3" relation="AUX"/><mor-post><mw><pos><c>neg</c></pos><stem>not</stem></mw><gra type="gra" index="2" head="1" relation="NEG"/></mor-post></mor></w>
    <w>Donna<mor type="mor"><mw><pos><c>n</c><s>prop</s></pos><stem>Donna</stem></mw><gra type="gra" index="3" head="0" relation="ROOT"/></mor></w>
    <w>no<mor type="mor"><mw><pos><c>co</c></pos><stem>no</stem></mw><gra type="gra" index="4" head="3" relation="COM"/></mor></w>
    <pause symbolic-length="simple" length="12"/>
    <t type="p"><mor type="mor"><mt type="p"/><gra type="gra" index="5" head="3" relation="PUNCT"/></mor></t>

  </u>
  <u who="MOT" uID="u85">
    <w>give<mor type="mor"><mw><pos><c>v</c></pos><stem>give</stem></mw><gra type="gra" index="1" head="0" relation="ROOT"/></mor></w>
    <w>that<mor type="mor"><mw><pos><c>adv</c></pos><stem>that</stem></mw><gra type="gra" index="2" head="1" relation="JCT"/></mor></w>
    <w>to<mor type="mor"><mw><pos><c>prep</c></pos><stem>to</stem></mw><gra type="gra" index="3" head="1" relation="JCT"/></mor></w>
    <w>Rosie<mor type="mor"><mw><pos><c>n</c><s>prop</s></pos><stem>Rosie</stem></mw><gra type="gra" index="4" head="3" relation="POBJ"/></mor></w>
    <pause symbolic-length="simple" length="15"/>
    <t type="p"><mor type="mor"><mt type="p"/><gra type="gra" index="5" head="1" relation="PUNCT"/></mor></t>

  </u>
  <u who="DON" uID="u86">
    <w>can't<mor type="mor"><mw><pos><c>mod</c></pos><stem>can</stem></mw><gra type="gra" index="1" head="3" relation="AUX"/><mor-post><mw><pos><c>neg</c></pos><stem>not</stem></mw><gra type="gra" index="2" head="1" relation="NEG"/></mor-post></mor></w>
    <w>get<mor type="mor"><mw><pos><c>v</c></pos><stem>get</stem></mw><gra type="gra" index="3" head="0" relation="ROOT"/></mor></w>
    <w>up<mor type="mor"><mw><pos><c>adv</c></pos><stem>up</stem></mw><gra type="gra" index="4" head="3" relation="JCT"/></mor></w>
    <pause symbolic-length="simple" length="12"/>
    <t type="p"><mor type="mor"><mt type="p"/><gra type="gra" index="5" head="3" relation="PUNCT"/></mor></t>

  </u>
  <u who="UNK" uID="u87">
    <e><action/><ga type="paralinguistics">screams</ga></e>
    <t type="p"></t>

  </u>
  <comment type="Location">Sitting room</comment>
  <comment type="Situation">Record player on throughout</comment>
  <comment type="Generic">R had dropped something on M's toe</comment>
  <comment type="Generic">one long screaming sound</comment>
  <u who="CHI" uID="u88">
    <w untranscribed="unintelligible-with-pho">yyy</w>
    <pause symbolic-length="simple" length="2"/>
    <t type="p"></t>

  </u>
  <u who="MOT" uID="u89">
    <w>stop<mor type="mor"><mw><pos><c>v</c></pos><stem>stop</stem></mw><gra type="gra" index="1" head="0" relation="ROOT"/></mor></w>
    <w>it<mor type="mor"><mw><pos><c>pro</c><s>per</s></pos><stem>it</stem></mw><gra type="gra" index="2" head="1" relation="OBJ"/></mor></w>
    <t type="p"><mor type="mor"><mt type="p"/><gra type="gra" index="3" head="1" relation="PUNCT"/></mor></t>

  </u>
  <u who="DON" uID="u90">
    <w untranscribed="unintelligible">xxx</w>
    <pause symbolic-length="simple" length="12"/>
    <t type="p"></t>

  </u>
  <comment type="Time Start">3:56</comment>
  <comment type="Activities">Free play alone</comment>
  <u who="MOT" uID="u91">
    <w untranscribed="unintelligible">xxx</w>
    <t type="q"></t>

  </u>
  <u who="MOT" uID="u92">
    <w>oh<mor type="mor"><mw><pos><c>co</c></pos><stem>oh</stem></mw><gra type="gra" index="1" head="0" relation="INCROOT"/></mor></w>
    <pause symbolic-length="simple" length="3"/>
    <t type="p"><mor type="mor"><mt type="p"/><gra type="gra" index="2" head="1" relation="PUNCT"/></mor></t>

  </u>
  <u who="KEL" uID="u93">
    <w untranscribed="unintelligible">xxx</w>
    <pause symbolic-length="simple" length="2"/>
    <t type="p"></t>

    <a type="comments">singing with record</a>
    <a type="addressee">to K</a>
  </u>
  <u who="KEL" uID="u94">
    <w untranscribed="unintelligible">xxx</w>
    <pause symbolic-length="simple" length="24"/>
    <t type="p"></t>

  </u>
  <u who="MOT" uID="u95">
    <w>you<mor type="mor"><mw><pos><c>pro</c><s>per</s></pos><stem>you</stem></mw><gra type="gra" index="1" head="2" relation="SUBJ"/></mor></w>
    <w>see<mor type="mor"><mw><pos><c>v</c></pos><stem>see</stem></mw><gra type="gra" index="2" head="0" relation="ROOT"/></mor></w>
    <w>it<mor type="mor"><mw><pos><c>pro</c><s>per</s></pos><stem>it</stem></mw><gra type="gra" index="3" head="2" relation="OBJ"/></mor></w>
    <w>by<mor type="mor"><mw><pos><c>prep</c></pos><stem>by</stem></mw><gra type="gra" index="4" head="2" relation="JCT"/></mor></w>
    <w>the<mor type="mor"><mw><pos><c>det</c><s>art</s></pos><stem>the</stem></mw><gra type="gra" index="5" head="6" relation="DET"/></mor></w>
    <w>door<mor type="mor"><mw><pos><c>n</c></pos><stem>door</stem></mw><gra type="gra" index="6" head="4" relation="POBJ"/></mor></w>
    <pause symbolic-length="simple" length="9"/>
    <t type="p"><mor type="mor"><mt type="p"/><gra type="gra" index="7" head="2" relation="PUNCT"/></mor></t>

  </u>
  <u who="MOT" uID="u96">
    <w>I<mor type="mor"><mw><pos><c>pro</c><s>sub</s></pos><stem>I</stem></mw><gra type="gra" index="1" head="3" relation="SUBJ"/></mor></w>
    <w>just<mor type="mor"><mw><pos><c>adv</c></pos><stem>just</stem></mw><gra type="gra" index="2" head="3" relation="JCT"/></mor></w>
    <w>wanna<mor type="mor"><mw><pos><c>v</c></pos><stem>want</stem></mw><gra type="gra" index="3" head="0" relation="ROOT"/><mor-post><mw><pos><c>inf</c></pos><stem>to</stem></mw><gra type="gra" index="4" head="5" relation="INF"/></mor-post></mor></w>
    <w>say<mor type="mor"><mw><pos><c>co</c></pos><stem>say</stem></mw><gra type="gra" index="5" head="7" relation="COM"/></mor></w>
    <w>bye<mor type="mor"><mw><pos><c>co</c></pos><stem>bye</stem></mw><gra type="gra" index="6" head="7" relation="COM"/></mor></w>
    <w>bye<mor type="mor"><mw><pos><c>co</c></pos><stem>bye</stem></mw><gra type="gra" index="7" head="3" relation="COMP"/></mor></w>
    <pause symbolic-length="simple" length="20"/>
    <t type="p"><mor type="mor"><mt type="p"/><gra type="gra" index="8" head="3" relation="PUNCT"/></mor></t>

  </u>
  <u who="MOT" uID="u97">
    <w>bring<mor type="mor"><mw><pos><c>v</c></pos><stem>bring</stem></mw><gra type="gra" index="1" head="0" relation="ROOT"/></mor></w>
    <w>it<mor type="mor"><mw><pos><c>pro</c><s>per</s></pos><stem>it</stem></mw><gra type="gra" index="2" head="1" relation="OBJ"/></mor></w>
    <w>in<mor type="mor"><mw><pos><c>prep</c></pos><stem>in</stem></mw><gra type="gra" index="3" head="1" relation="JCT"/></mor></w>
    <w>here<mor type="mor"><mw><pos><c>n</c></pos><stem>here</stem></mw><gra type="gra" index="4" head="3" relation="POBJ"/></mor></w>
    <pause symbolic-length="simple" length="3"/>
    <t type="p"><mor type="mor"><mt type="p"/><gra type="gra" index="5" head="1" relation="PUNCT"/></mor></t>

  </u>
  <u who="MOT" uID="u98">
    <w>Kelvin<mor type="mor"><mw><pos><c>n</c><s>prop</s></pos><stem>Kelvin</stem></mw><gra type="gra" index="1" head="0" relation="INCROOT"/></mor></w>
    <t type="p"><mor type="mor"><mt type="p"/><gra type="gra" index="2" head="1" relation="PUNCT"/></mor></t>

  </u>
</CHAT>